{
"meta":{"launch_mode":"Train","name":"experiment","iteration_count":1000,"learn_metrics":[{"best_value":"Min","name":"RMSE"}],"test_sets":[],"test_metrics":[],"learn_sets":["learn"]},
"iterations":[
{"learn":[0.5318943777],"iteration":0,"passed_time":0.007719652976,"remaining_time":7.711933323},
{"learn":[0.5270476211],"iteration":1,"passed_time":0.01394621609,"remaining_time":6.95916183},
{"learn":[0.5216374969],"iteration":2,"passed_time":0.02089175497,"remaining_time":6.943026567},
{"learn":[0.5162136626],"iteration":3,"passed_time":0.02778046219,"remaining_time":6.917335085},
{"learn":[0.5114370604],"iteration":4,"passed_time":0.03252494614,"remaining_time":6.472464283},
{"learn":[0.5066374839],"iteration":5,"passed_time":0.039438831,"remaining_time":6.533699669},
{"learn":[0.5023635422],"iteration":6,"passed_time":0.046562869,"remaining_time":6.60527556},
{"learn":[0.4979026618],"iteration":7,"passed_time":0.05192898544,"remaining_time":6.439194194},
{"learn":[0.4938842765],"iteration":8,"passed_time":0.05541727778,"remaining_time":6.102058031},
{"learn":[0.4899751212],"iteration":9,"passed_time":0.05900890644,"remaining_time":5.841881738},
{"learn":[0.4860754588],"iteration":10,"passed_time":0.06576092228,"remaining_time":5.912504739},
{"learn":[0.4825182292],"iteration":11,"passed_time":0.07241049136,"remaining_time":5.961797122},
{"learn":[0.4789296576],"iteration":12,"passed_time":0.0792335887,"remaining_time":6.01565785},
{"learn":[0.4754844358],"iteration":13,"passed_time":0.08626687275,"remaining_time":6.075652609},
{"learn":[0.4723137883],"iteration":14,"passed_time":0.09317460452,"remaining_time":6.118465697},
{"learn":[0.4694471663],"iteration":15,"passed_time":0.1000444801,"remaining_time":6.152735529},
{"learn":[0.4662520208],"iteration":16,"passed_time":0.1068531792,"remaining_time":6.178627951},
{"learn":[0.4635498991],"iteration":17,"passed_time":0.1124216247,"remaining_time":6.13322419},
{"learn":[0.4611181175],"iteration":18,"passed_time":0.1192178982,"remaining_time":6.155408322},
{"learn":[0.4582302565],"iteration":19,"passed_time":0.1259020368,"remaining_time":6.169199804},
{"learn":[0.4556210671],"iteration":20,"passed_time":0.1325448575,"remaining_time":6.179115024},
{"learn":[0.4533211127],"iteration":21,"passed_time":0.1393308092,"remaining_time":6.193887791},
{"learn":[0.4508438189],"iteration":22,"passed_time":0.147175242,"remaining_time":6.251748324},
{"learn":[0.4483938459],"iteration":23,"passed_time":0.1550088238,"remaining_time":6.303692169},
{"learn":[0.4465991301],"iteration":24,"passed_time":0.1620568166,"remaining_time":6.320215846},
{"learn":[0.4438364878],"iteration":25,"passed_time":0.1690115392,"remaining_time":6.331432278},
{"learn":[0.4417798332],"iteration":26,"passed_time":0.1761763605,"remaining_time":6.34887403},
{"learn":[0.4396573881],"iteration":27,"passed_time":0.1827537062,"remaining_time":6.344164373},
{"learn":[0.4378417081],"iteration":28,"passed_time":0.1894652795,"remaining_time":6.34382022},
{"learn":[0.4355171645],"iteration":29,"passed_time":0.1962003232,"remaining_time":6.34381045},
{"learn":[0.433691305],"iteration":30,"passed_time":0.2028900267,"remaining_time":6.341949545},
{"learn":[0.431968149],"iteration":31,"passed_time":0.210599537,"remaining_time":6.370635993},
{"learn":[0.4300864205],"iteration":32,"passed_time":0.2174692909,"remaining_time":6.372509222},
{"learn":[0.4282716414],"iteration":33,"passed_time":0.2247731671,"remaining_time":6.386202336},
{"learn":[0.4267235912],"iteration":34,"passed_time":0.2318762375,"remaining_time":6.39315912},
{"learn":[0.4248462094],"iteration":35,"passed_time":0.2390156379,"remaining_time":6.400307637},
{"learn":[0.4234799882],"iteration":36,"passed_time":0.2455985917,"remaining_time":6.392201184},
{"learn":[0.4225381675],"iteration":37,"passed_time":0.2500565249,"remaining_time":6.33037834},
{"learn":[0.4210422065],"iteration":38,"passed_time":0.2575465168,"remaining_time":6.346210325},
{"learn":[0.4192007969],"iteration":39,"passed_time":0.2644757699,"remaining_time":6.347418477},
{"learn":[0.4178137567],"iteration":40,"passed_time":0.2713697493,"remaining_time":6.347404624},
{"learn":[0.4166622331],"iteration":41,"passed_time":0.2769243679,"remaining_time":6.316512963},
{"learn":[0.4153392137],"iteration":42,"passed_time":0.2844078731,"remaining_time":6.329728712},
{"learn":[0.4144141983],"iteration":43,"passed_time":0.2896293166,"remaining_time":6.292855152},
{"learn":[0.4134448897],"iteration":44,"passed_time":0.296327326,"remaining_time":6.288724363},
{"learn":[0.412095072],"iteration":45,"passed_time":0.3030119499,"remaining_time":6.284204352},
{"learn":[0.4106937206],"iteration":46,"passed_time":0.3097649218,"remaining_time":6.280978095},
{"learn":[0.4093808857],"iteration":47,"passed_time":0.316562867,"remaining_time":6.278496862},
{"learn":[0.4084548305],"iteration":48,"passed_time":0.3233164287,"remaining_time":6.274978034},
{"learn":[0.4074418214],"iteration":49,"passed_time":0.3303086339,"remaining_time":6.275864043},
{"learn":[0.4065020385],"iteration":50,"passed_time":0.3367820198,"remaining_time":6.266786997},
{"learn":[0.4052889737],"iteration":51,"passed_time":0.3437437316,"remaining_time":6.266712646},
{"learn":[0.4044600541],"iteration":52,"passed_time":0.3504685616,"remaining_time":6.262145808},
{"learn":[0.4037229371],"iteration":53,"passed_time":0.3575250105,"remaining_time":6.263308518},
{"learn":[0.4029824238],"iteration":54,"passed_time":0.3643674435,"remaining_time":6.260495165},
{"learn":[0.4018928203],"iteration":55,"passed_time":0.3711182406,"remaining_time":6.255993199},
{"learn":[0.4005556074],"iteration":56,"passed_time":0.3780602851,"remaining_time":6.254576296},
{"learn":[0.3995656099],"iteration":57,"passed_time":0.384686043,"remaining_time":6.24783194},
{"learn":[0.3985693577],"iteration":58,"passed_time":0.3915386952,"remaining_time":6.244710376},
{"learn":[0.3977740816],"iteration":59,"passed_time":0.3982386728,"remaining_time":6.23907254},
{"learn":[0.396960335],"iteration":60,"passed_time":0.4050684007,"remaining_time":6.235397185},
{"learn":[0.3958638088],"iteration":61,"passed_time":0.4132451156,"remaining_time":6.251998684},
{"learn":[0.3947803916],"iteration":62,"passed_time":0.4200483223,"remaining_time":6.247385366},
{"learn":[0.3940849769],"iteration":63,"passed_time":0.4268874558,"remaining_time":6.243229041},
{"learn":[0.3931254561],"iteration":64,"passed_time":0.4334643852,"remaining_time":6.235218465},
{"learn":[0.3928157479],"iteration":65,"passed_time":0.436797505,"remaining_time":6.18134651},
{"learn":[0.3919981039],"iteration":66,"passed_time":0.4434197514,"remaining_time":6.174785494},
{"learn":[0.3910710947],"iteration":67,"passed_time":0.450009584,"remaining_time":6.167778415},
{"learn":[0.3901790877],"iteration":68,"passed_time":0.4568435313,"remaining_time":6.164077212},
{"learn":[0.3891739832],"iteration":69,"passed_time":0.4639569174,"remaining_time":6.163999046},
{"learn":[0.3885715985],"iteration":70,"passed_time":0.471095316,"remaining_time":6.164049979},
{"learn":[0.3881527708],"iteration":71,"passed_time":0.4755907004,"remaining_time":6.129835693},
{"learn":[0.3872393022],"iteration":72,"passed_time":0.482471899,"remaining_time":6.126732197},
{"learn":[0.3868715245],"iteration":73,"passed_time":0.4876612787,"remaining_time":6.102356001},
{"learn":[0.3861502627],"iteration":74,"passed_time":0.4942458513,"remaining_time":6.095698832},
{"learn":[0.3856230741],"iteration":75,"passed_time":0.4994847557,"remaining_time":6.072683082},
{"learn":[0.3850031341],"iteration":76,"passed_time":0.5062529773,"remaining_time":6.068461014},
{"learn":[0.3843369444],"iteration":77,"passed_time":0.5126124809,"remaining_time":6.059342403},
{"learn":[0.3837487907],"iteration":78,"passed_time":0.5189893913,"remaining_time":6.050496574},
{"learn":[0.3830620133],"iteration":79,"passed_time":0.5257358219,"remaining_time":6.045961952},
{"learn":[0.382470224],"iteration":80,"passed_time":0.5322101672,"remaining_time":6.038285724},
{"learn":[0.3818289585],"iteration":81,"passed_time":0.5388611769,"remaining_time":6.03261659},
{"learn":[0.3813413538],"iteration":82,"passed_time":0.5458180808,"remaining_time":6.030303374},
{"learn":[0.3808074224],"iteration":83,"passed_time":0.5521562254,"remaining_time":6.021132172},
{"learn":[0.3804992333],"iteration":84,"passed_time":0.5589511531,"remaining_time":6.016944766},
{"learn":[0.3802207907],"iteration":85,"passed_time":0.5656421505,"remaining_time":6.011592157},
{"learn":[0.3798356597],"iteration":86,"passed_time":0.5728543289,"remaining_time":6.011678187},
{"learn":[0.3795771542],"iteration":87,"passed_time":0.5761851262,"remaining_time":5.971373126},
{"learn":[0.3788584213],"iteration":88,"passed_time":0.5830023899,"remaining_time":5.96758626},
{"learn":[0.377853959],"iteration":89,"passed_time":0.5898372794,"remaining_time":5.963910269},
{"learn":[0.3770510668],"iteration":90,"passed_time":0.5967741868,"remaining_time":5.96118391},
{"learn":[0.3764226934],"iteration":91,"passed_time":0.6035395262,"remaining_time":5.956672715},
{"learn":[0.3758170118],"iteration":92,"passed_time":0.6108650704,"remaining_time":5.957576547},
{"learn":[0.3751756834],"iteration":93,"passed_time":0.618554301,"remaining_time":5.961810603},
{"learn":[0.3746405596],"iteration":94,"passed_time":0.6251741917,"remaining_time":5.955606773},
{"learn":[0.3740949921],"iteration":95,"passed_time":0.6318783115,"remaining_time":5.950187434},
{"learn":[0.3736442893],"iteration":96,"passed_time":0.6388479665,"remaining_time":5.947213544},
{"learn":[0.3733097283],"iteration":97,"passed_time":0.6456722422,"remaining_time":5.942820025},
{"learn":[0.3727642339],"iteration":98,"passed_time":0.6526908617,"remaining_time":5.940146126},
{"learn":[0.3721413248],"iteration":99,"passed_time":0.6593750662,"remaining_time":5.934375596},
{"learn":[0.3715429508],"iteration":100,"passed_time":0.6663315651,"remaining_time":5.931010664},
{"learn":[0.3708824185],"iteration":101,"passed_time":0.6729576141,"remaining_time":5.924666053},
{"learn":[0.3704697431],"iteration":102,"passed_time":0.6803095233,"remaining_time":5.924637305},
{"learn":[0.3700979054],"iteration":103,"passed_time":0.6880797106,"remaining_time":5.928071353},
{"learn":[0.3697208588],"iteration":104,"passed_time":0.6934952889,"remaining_time":5.911221748},
{"learn":[0.3691179518],"iteration":105,"passed_time":0.700491185,"remaining_time":5.90791622},
{"learn":[0.3686936909],"iteration":106,"passed_time":0.7073347611,"remaining_time":5.903270483},
{"learn":[0.3681596374],"iteration":107,"passed_time":0.7142751829,"remaining_time":5.899383918},
{"learn":[0.3676045299],"iteration":108,"passed_time":0.7211203736,"remaining_time":5.894662871},
{"learn":[0.367305443],"iteration":109,"passed_time":0.726762146,"remaining_time":5.880166454},
{"learn":[0.3667435226],"iteration":110,"passed_time":0.7337851443,"remaining_time":5.876891832},
{"learn":[0.3661617155],"iteration":111,"passed_time":0.7408282756,"remaining_time":5.873709899},
{"learn":[0.3654549021],"iteration":112,"passed_time":0.74792519,"remaining_time":5.870881801},
{"learn":[0.3646238446],"iteration":113,"passed_time":0.7548983977,"remaining_time":5.867017372},
{"learn":[0.3641797005],"iteration":114,"passed_time":0.7622321246,"remaining_time":5.865873306},
{"learn":[0.363582063],"iteration":115,"passed_time":0.7694591956,"remaining_time":5.863809732},
{"learn":[0.3632027104],"iteration":116,"passed_time":0.776259481,"remaining_time":5.858436938},
{"learn":[0.3628132493],"iteration":117,"passed_time":0.7831975804,"remaining_time":5.85407005},
{"learn":[0.3623011196],"iteration":118,"passed_time":0.7899407506,"remaining_time":5.848216817},
{"learn":[0.3615719681],"iteration":119,"passed_time":0.7968912948,"remaining_time":5.843869495},
{"learn":[0.3612392606],"iteration":120,"passed_time":0.8041448854,"remaining_time":5.841680614},
{"learn":[0.3605166643],"iteration":121,"passed_time":0.812475135,"remaining_time":5.847157119},
{"learn":[0.3600011374],"iteration":122,"passed_time":0.8192760912,"remaining_time":5.841505138},
{"learn":[0.3597270703],"iteration":123,"passed_time":0.8237512114,"remaining_time":5.81940372},
{"learn":[0.3590692408],"iteration":124,"passed_time":0.8313197412,"remaining_time":5.819238188},
{"learn":[0.3585366012],"iteration":125,"passed_time":0.8393042517,"remaining_time":5.821840603},
{"learn":[0.3578860731],"iteration":126,"passed_time":0.8482926438,"remaining_time":5.831176992},
{"learn":[0.3574345963],"iteration":127,"passed_time":0.8566619576,"remaining_time":5.836009586},
{"learn":[0.3568479328],"iteration":128,"passed_time":0.8644557896,"remaining_time":5.836751882},
{"learn":[0.3558961761],"iteration":129,"passed_time":0.8720108871,"remaining_time":5.835765167},
{"learn":[0.3552338457],"iteration":130,"passed_time":0.8793231372,"remaining_time":5.833067223},
{"learn":[0.3545826061],"iteration":131,"passed_time":0.8867058809,"remaining_time":5.830762914},
{"learn":[0.3541838332],"iteration":132,"passed_time":0.8939579085,"remaining_time":5.827530125},
{"learn":[0.3536763809],"iteration":133,"passed_time":0.9007301679,"remaining_time":5.821136757},
{"learn":[0.3534103362],"iteration":134,"passed_time":0.9074471054,"remaining_time":5.814383305},
{"learn":[0.3527970369],"iteration":135,"passed_time":0.9141046693,"remaining_time":5.807253193},
{"learn":[0.3524044442],"iteration":136,"passed_time":0.9220486601,"remaining_time":5.80823353},
{"learn":[0.3515152421],"iteration":137,"passed_time":0.9300006915,"remaining_time":5.809134754},
{"learn":[0.351192462],"iteration":138,"passed_time":0.9430516539,"remaining_time":5.841492619},
{"learn":[0.3507935903],"iteration":139,"passed_time":0.9503488107,"remaining_time":5.83785698},
{"learn":[0.3505798588],"iteration":140,"passed_time":0.9556953776,"remaining_time":5.822286024},
{"learn":[0.3501730093],"iteration":141,"passed_time":0.9632587087,"remaining_time":5.820253324},
{"learn":[0.34974095],"iteration":142,"passed_time":0.969731107,"remaining_time":5.811605306},
{"learn":[0.3494066921],"iteration":143,"passed_time":0.9772872719,"remaining_time":5.809429894},
{"learn":[0.3488936228],"iteration":144,"passed_time":0.9837125441,"remaining_time":5.800511898},
{"learn":[0.3483457446],"iteration":145,"passed_time":0.9904832502,"remaining_time":5.793648601},
{"learn":[0.3480510952],"iteration":146,"passed_time":0.9972969679,"remaining_time":5.787036147},
{"learn":[0.3478913064],"iteration":147,"passed_time":1.001391962,"remaining_time":5.764769946},
{"learn":[0.347156469],"iteration":148,"passed_time":1.008508194,"remaining_time":5.760003175},
{"learn":[0.3468583114],"iteration":149,"passed_time":1.016711924,"remaining_time":5.761367568},
{"learn":[0.3460250952],"iteration":150,"passed_time":1.023697774,"remaining_time":5.75575768},
{"learn":[0.3455743452],"iteration":151,"passed_time":1.030263583,"remaining_time":5.747786306},
{"learn":[0.3452047797],"iteration":152,"passed_time":1.036993873,"remaining_time":5.740743858},
{"learn":[0.3447927648],"iteration":153,"passed_time":1.043578827,"remaining_time":5.732907065},
{"learn":[0.3444136411],"iteration":154,"passed_time":1.052095481,"remaining_time":5.735617301},
{"learn":[0.3437749085],"iteration":155,"passed_time":1.058925395,"remaining_time":5.729057907},
{"learn":[0.3433169803],"iteration":156,"passed_time":1.065860764,"remaining_time":5.723061302},
{"learn":[0.343026173],"iteration":157,"passed_time":1.072677111,"remaining_time":5.716418529},
{"learn":[0.3424776421],"iteration":158,"passed_time":1.079276433,"remaining_time":5.708625662},
{"learn":[0.3419149347],"iteration":159,"passed_time":1.08609301,"remaining_time":5.701988302},
{"learn":[0.3414714712],"iteration":160,"passed_time":1.092620341,"remaining_time":5.693841403},
{"learn":[0.3409914614],"iteration":161,"passed_time":1.099324204,"remaining_time":5.686627673},
{"learn":[0.3404461013],"iteration":162,"passed_time":1.106759032,"remaining_time":5.683173682},
{"learn":[0.3398329144],"iteration":163,"passed_time":1.11349083,"remaining_time":5.6760874},
{"learn":[0.3394890293],"iteration":164,"passed_time":1.119938488,"remaining_time":5.667567502},
{"learn":[0.3389244341],"iteration":165,"passed_time":1.12678978,"remaining_time":5.661100459},
{"learn":[0.3386709505],"iteration":166,"passed_time":1.133371633,"remaining_time":5.653284853},
{"learn":[0.338231072],"iteration":167,"passed_time":1.140140658,"remaining_time":5.646410879},
{"learn":[0.3378627181],"iteration":168,"passed_time":1.146712056,"remaining_time":5.638566384},
{"learn":[0.3372322397],"iteration":169,"passed_time":1.153548703,"remaining_time":5.632031902},
{"learn":[0.3367999413],"iteration":170,"passed_time":1.160239933,"remaining_time":5.624788915},
{"learn":[0.3363504034],"iteration":171,"passed_time":1.166767002,"remaining_time":5.616762079},
{"learn":[0.3359482018],"iteration":172,"passed_time":1.173578907,"remaining_time":5.610114198},
{"learn":[0.3354332635],"iteration":173,"passed_time":1.180322631,"remaining_time":5.603140768},
{"learn":[0.3350280399],"iteration":174,"passed_time":1.187314501,"remaining_time":5.597339792},
{"learn":[0.3346649196],"iteration":175,"passed_time":1.193961353,"remaining_time":5.589909973},
{"learn":[0.3343960832],"iteration":176,"passed_time":1.200884185,"remaining_time":5.583772228},
{"learn":[0.3341478303],"iteration":177,"passed_time":1.20757126,"remaining_time":5.576536942},
{"learn":[0.333421991],"iteration":178,"passed_time":1.216206901,"remaining_time":5.57824506},
{"learn":[0.3330745331],"iteration":179,"passed_time":1.222702428,"remaining_time":5.570088838},
{"learn":[0.3327608485],"iteration":180,"passed_time":1.229383815,"remaining_time":5.562791961},
{"learn":[0.3321309983],"iteration":181,"passed_time":1.235987476,"remaining_time":5.555152503},
{"learn":[0.3317622711],"iteration":182,"passed_time":1.243444829,"remaining_time":5.551335656},
{"learn":[0.3313901268],"iteration":183,"passed_time":1.250197699,"remaining_time":5.544355013},
{"learn":[0.3309927852],"iteration":184,"passed_time":1.257072917,"remaining_time":5.537915824},
{"learn":[0.3305308039],"iteration":185,"passed_time":1.263934897,"remaining_time":5.53141401},
{"learn":[0.3299156423],"iteration":186,"passed_time":1.270624684,"remaining_time":5.524159723},
{"learn":[0.3291984488],"iteration":187,"passed_time":1.278499846,"remaining_time":5.522031252},
{"learn":[0.3287530416],"iteration":188,"passed_time":1.285718741,"remaining_time":5.51702592},
{"learn":[0.3280119544],"iteration":189,"passed_time":1.293066332,"remaining_time":5.512545944},
{"learn":[0.3276140538],"iteration":190,"passed_time":1.299833953,"remaining_time":5.505579415},
{"learn":[0.3271037321],"iteration":191,"passed_time":1.307389275,"remaining_time":5.501929865},
{"learn":[0.3266912961],"iteration":192,"passed_time":1.314269363,"remaining_time":5.495416458},
{"learn":[0.3262842492],"iteration":193,"passed_time":1.320956859,"remaining_time":5.488099117},
{"learn":[0.3259280509],"iteration":194,"passed_time":1.327708757,"remaining_time":5.481054101},
{"learn":[0.3255977491],"iteration":195,"passed_time":1.334369303,"remaining_time":5.473637346},
{"learn":[0.325237246],"iteration":196,"passed_time":1.341262592,"remaining_time":5.467176962},
{"learn":[0.3249177742],"iteration":197,"passed_time":1.348083177,"remaining_time":5.460417719},
{"learn":[0.3244027852],"iteration":198,"passed_time":1.354577805,"remaining_time":5.452345839},
{"learn":[0.3238257364],"iteration":199,"passed_time":1.361371451,"remaining_time":5.445485804},
{"learn":[0.32353655],"iteration":200,"passed_time":1.367808957,"remaining_time":5.437210732},
{"learn":[0.3229705972],"iteration":201,"passed_time":1.374596275,"remaining_time":5.430335778},
{"learn":[0.3227033362],"iteration":202,"passed_time":1.381223155,"remaining_time":5.422831797},
{"learn":[0.3222820068],"iteration":203,"passed_time":1.387873907,"remaining_time":5.41542956},
{"learn":[0.3219264858],"iteration":204,"passed_time":1.394205503,"remaining_time":5.406796951},
{"learn":[0.3216008643],"iteration":205,"passed_time":1.400873651,"remaining_time":5.399483878},
{"learn":[0.320976629],"iteration":206,"passed_time":1.407751663,"remaining_time":5.392981009},
{"learn":[0.3207657659],"iteration":207,"passed_time":1.414451964,"remaining_time":5.385797863},
{"learn":[0.3205041055],"iteration":208,"passed_time":1.422660168,"remaining_time":5.384326281},
{"learn":[0.3202101724],"iteration":209,"passed_time":1.429155441,"remaining_time":5.37634666},
{"learn":[0.3196706577],"iteration":210,"passed_time":1.435930469,"remaining_time":5.369427203},
{"learn":[0.3194428928],"iteration":211,"passed_time":1.442562725,"remaining_time":5.361978431},
{"learn":[0.3188545497],"iteration":212,"passed_time":1.449357533,"remaining_time":5.355137927},
{"learn":[0.3185877732],"iteration":213,"passed_time":1.456170867,"remaining_time":5.348365896},
{"learn":[0.31825169],"iteration":214,"passed_time":1.462651298,"remaining_time":5.340377996},
{"learn":[0.3180583661],"iteration":215,"passed_time":1.469500686,"remaining_time":5.333743232},
{"learn":[0.3179257424],"iteration":216,"passed_time":1.476082846,"remaining_time":5.326142252},
{"learn":[0.3175933171],"iteration":217,"passed_time":1.482799539,"remaining_time":5.31903321},
{"learn":[0.3170357238],"iteration":218,"passed_time":1.48949968,"remaining_time":5.311868722},
{"learn":[0.3166897529],"iteration":219,"passed_time":1.496100893,"remaining_time":5.304357713},
{"learn":[0.3162778331],"iteration":220,"passed_time":1.502943906,"remaining_time":5.297707251},
{"learn":[0.31597908],"iteration":221,"passed_time":1.509851005,"remaining_time":5.291279649},
{"learn":[0.3155024788],"iteration":222,"passed_time":1.517025946,"remaining_time":5.285780986},
{"learn":[0.3154776184],"iteration":223,"passed_time":1.520295399,"remaining_time":5.266737633},
{"learn":[0.3151746747],"iteration":224,"passed_time":1.527334789,"remaining_time":5.260819828},
{"learn":[0.31504039],"iteration":225,"passed_time":1.533929432,"remaining_time":5.25336894},
{"learn":[0.3146849932],"iteration":226,"passed_time":1.540305014,"remaining_time":5.245179628},
{"learn":[0.3143374509],"iteration":227,"passed_time":1.54717508,"remaining_time":5.238680533},
{"learn":[0.3138675111],"iteration":228,"passed_time":1.553805716,"remaining_time":5.231372085},
{"learn":[0.3134042182],"iteration":229,"passed_time":1.560384581,"remaining_time":5.223896207},
{"learn":[0.3133812608],"iteration":230,"passed_time":1.564945785,"remaining_time":5.209711294},
{"learn":[0.3131580791],"iteration":231,"passed_time":1.571597916,"remaining_time":5.202531033},
{"learn":[0.3129663239],"iteration":232,"passed_time":1.5782342,"remaining_time":5.195303138},
{"learn":[0.3125035929],"iteration":233,"passed_time":1.585980948,"remaining_time":5.191715412},
{"learn":[0.3121911117],"iteration":234,"passed_time":1.592801591,"remaining_time":5.185077518},
{"learn":[0.31157199],"iteration":235,"passed_time":1.599853848,"remaining_time":5.179187879},
{"learn":[0.3112963725],"iteration":236,"passed_time":1.60653305,"remaining_time":5.172087414},
{"learn":[0.3110148899],"iteration":237,"passed_time":1.613450262,"remaining_time":5.16575252},
{"learn":[0.3107163504],"iteration":238,"passed_time":1.621607914,"remaining_time":5.163362438},
{"learn":[0.3104391575],"iteration":239,"passed_time":1.628804838,"remaining_time":5.157881988},
{"learn":[0.3102177345],"iteration":240,"passed_time":1.6354893,"remaining_time":5.150773354},
{"learn":[0.3097787064],"iteration":241,"passed_time":1.642457607,"remaining_time":5.144557297},
{"learn":[0.3095316847],"iteration":242,"passed_time":1.649738766,"remaining_time":5.139309655},
{"learn":[0.309280829],"iteration":243,"passed_time":1.656545947,"remaining_time":5.132576787},
{"learn":[0.3088521916],"iteration":244,"passed_time":1.663532971,"remaining_time":5.126397523},
{"learn":[0.3082158825],"iteration":245,"passed_time":1.670947341,"remaining_time":5.121521525},
{"learn":[0.3075390876],"iteration":246,"passed_time":1.678038111,"remaining_time":5.11563845},
{"learn":[0.3070739376],"iteration":247,"passed_time":1.684715107,"remaining_time":5.108490968},
{"learn":[0.3067111238],"iteration":248,"passed_time":1.691331359,"remaining_time":5.101164058},
{"learn":[0.3061627383],"iteration":249,"passed_time":1.69876431,"remaining_time":5.09629293},
{"learn":[0.305857474],"iteration":250,"passed_time":1.705521018,"remaining_time":5.089383435},
{"learn":[0.3052620412],"iteration":251,"passed_time":1.712185366,"remaining_time":5.082201008},
{"learn":[0.304765335],"iteration":252,"passed_time":1.718807456,"remaining_time":5.074897904},
{"learn":[0.3044633903],"iteration":253,"passed_time":1.726064056,"remaining_time":5.069463723},
{"learn":[0.3039749066],"iteration":254,"passed_time":1.734202386,"remaining_time":5.066591284},
{"learn":[0.3037310802],"iteration":255,"passed_time":1.741013757,"remaining_time":5.059821232},
{"learn":[0.3029834224],"iteration":256,"passed_time":1.747804117,"remaining_time":5.052990113},
{"learn":[0.3026461328],"iteration":257,"passed_time":1.754513771,"remaining_time":5.045927202},
{"learn":[0.3019725695],"iteration":258,"passed_time":1.761534964,"remaining_time":5.039758332},
{"learn":[0.3017742181],"iteration":259,"passed_time":1.768206643,"remaining_time":5.032588136},
{"learn":[0.3013046433],"iteration":260,"passed_time":1.774810223,"remaining_time":5.025228945},
{"learn":[0.3009865517],"iteration":261,"passed_time":1.781204809,"remaining_time":5.017286829},
{"learn":[0.3006917614],"iteration":262,"passed_time":1.788193327,"remaining_time":5.011020845},
{"learn":[0.3002631582],"iteration":263,"passed_time":1.794931725,"remaining_time":5.004052081},
{"learn":[0.2999057781],"iteration":264,"passed_time":1.801599573,"remaining_time":4.996889382},
{"learn":[0.2994874267],"iteration":265,"passed_time":1.808281682,"remaining_time":4.989769755},
{"learn":[0.2991134116],"iteration":266,"passed_time":1.814734054,"remaining_time":4.982022703},
{"learn":[0.2986686254],"iteration":267,"passed_time":1.821712912,"remaining_time":4.975723327},
{"learn":[0.298128621],"iteration":268,"passed_time":1.829795255,"remaining_time":4.972417588},
{"learn":[0.2977747982],"iteration":269,"passed_time":1.837440119,"remaining_time":4.967893654},
{"learn":[0.2973450501],"iteration":270,"passed_time":1.844721741,"remaining_time":4.962369554},
{"learn":[0.2970295643],"iteration":271,"passed_time":1.852702991,"remaining_time":4.958705063},
{"learn":[0.2963897214],"iteration":272,"passed_time":1.860547978,"remaining_time":4.95464608},
{"learn":[0.2960150927],"iteration":273,"passed_time":1.867744545,"remaining_time":4.948841386},
{"learn":[0.2956383872],"iteration":274,"passed_time":1.875423312,"remaining_time":4.944297821},
{"learn":[0.2952352107],"iteration":275,"passed_time":1.883951443,"remaining_time":4.941959581},
{"learn":[0.2947482752],"iteration":276,"passed_time":1.890533505,"remaining_time":4.934497198},
{"learn":[0.2943002002],"iteration":277,"passed_time":1.896766533,"remaining_time":4.926134664},
{"learn":[0.2940972005],"iteration":278,"passed_time":1.903044415,"remaining_time":4.91790331},
{"learn":[0.2937938681],"iteration":279,"passed_time":1.909541093,"remaining_time":4.910248526},
{"learn":[0.2934968015],"iteration":280,"passed_time":1.915704793,"remaining_time":4.901749987},
{"learn":[0.2930353798],"iteration":281,"passed_time":1.922228221,"remaining_time":4.894183909},
{"learn":[0.2926845282],"iteration":282,"passed_time":1.928407714,"remaining_time":4.885753818},
{"learn":[0.2924161939],"iteration":283,"passed_time":1.934598567,"remaining_time":4.877368219},
{"learn":[0.2920306079],"iteration":284,"passed_time":1.941086467,"remaining_time":4.869743241},
{"learn":[0.2917426791],"iteration":285,"passed_time":1.947367504,"remaining_time":4.861609783},
{"learn":[0.2913968291],"iteration":286,"passed_time":1.954114918,"remaining_time":4.854647864},
{"learn":[0.2909177516],"iteration":287,"passed_time":1.960652201,"remaining_time":4.847167941},
{"learn":[0.2907790056],"iteration":288,"passed_time":1.967499618,"remaining_time":4.840457537},
{"learn":[0.2904223547],"iteration":289,"passed_time":1.973946408,"remaining_time":4.832765344},
{"learn":[0.2900251453],"iteration":290,"passed_time":1.980474613,"remaining_time":4.825280071},
{"learn":[0.2895901856],"iteration":291,"passed_time":1.987309891,"remaining_time":4.818545899},
{"learn":[0.28916911],"iteration":292,"passed_time":1.994228957,"remaining_time":4.812013216},
{"learn":[0.288832245],"iteration":293,"passed_time":2.000893457,"remaining_time":4.804866601},
{"learn":[0.2883302882],"iteration":294,"passed_time":2.007563137,"remaining_time":4.797735632},
{"learn":[0.2879749017],"iteration":295,"passed_time":2.014424693,"remaining_time":4.791064135},
{"learn":[0.2876571845],"iteration":296,"passed_time":2.021033444,"remaining_time":4.783792967},
{"learn":[0.2872626152],"iteration":297,"passed_time":2.029234924,"remaining_time":4.780278243},
{"learn":[0.2868804812],"iteration":298,"passed_time":2.036194315,"remaining_time":4.773820116},
{"learn":[0.2866685568],"iteration":299,"passed_time":2.043363901,"remaining_time":4.767849102},
{"learn":[0.2863953338],"iteration":300,"passed_time":2.051023313,"remaining_time":4.763007626},
{"learn":[0.2860974808],"iteration":301,"passed_time":2.057522029,"remaining_time":4.755464821},
{"learn":[0.2855136598],"iteration":302,"passed_time":2.064444368,"remaining_time":4.748903382},
{"learn":[0.2851202761],"iteration":303,"passed_time":2.071063849,"remaining_time":4.741646181},
{"learn":[0.2848812332],"iteration":304,"passed_time":2.077687372,"remaining_time":4.734402373},
{"learn":[0.2845590051],"iteration":305,"passed_time":2.084484035,"remaining_time":4.727555295},
{"learn":[0.284275976],"iteration":306,"passed_time":2.091049712,"remaining_time":4.720187135},
{"learn":[0.2839993667],"iteration":307,"passed_time":2.097633375,"remaining_time":4.712864595},
{"learn":[0.2836679132],"iteration":308,"passed_time":2.104213379,"remaining_time":4.705538657},
{"learn":[0.2834884982],"iteration":309,"passed_time":2.110837751,"remaining_time":4.698316284},
{"learn":[0.2831397093],"iteration":310,"passed_time":2.117398913,"remaining_time":4.690957719},
{"learn":[0.2829865965],"iteration":311,"passed_time":2.123990553,"remaining_time":4.683671475},
{"learn":[0.2827478606],"iteration":312,"passed_time":2.130597824,"remaining_time":4.676423977},
{"learn":[0.2824661254],"iteration":313,"passed_time":2.137378688,"remaining_time":4.669559809},
{"learn":[0.2822524751],"iteration":314,"passed_time":2.144140502,"remaining_time":4.662654742},
{"learn":[0.2817640644],"iteration":315,"passed_time":2.151094003,"remaining_time":4.656165499},
{"learn":[0.2815584984],"iteration":316,"passed_time":2.157790804,"remaining_time":4.649120249},
{"learn":[0.2814216654],"iteration":317,"passed_time":2.164633021,"remaining_time":4.642389057},
{"learn":[0.2811017304],"iteration":318,"passed_time":2.171494569,"remaining_time":4.635698436},
{"learn":[0.2807866283],"iteration":319,"passed_time":2.177993669,"remaining_time":4.628236546},
{"learn":[0.2806427602],"iteration":320,"passed_time":2.184709154,"remaining_time":4.621238367},
{"learn":[0.2804045965],"iteration":321,"passed_time":2.191403655,"remaining_time":4.614197759},
{"learn":[0.2801619948],"iteration":322,"passed_time":2.198224862,"remaining_time":4.607424866},
{"learn":[0.2798996812],"iteration":323,"passed_time":2.204973936,"remaining_time":4.600501175},
{"learn":[0.2793814764],"iteration":324,"passed_time":2.212164717,"remaining_time":4.59449595},
{"learn":[0.2792239089],"iteration":325,"passed_time":2.218948552,"remaining_time":4.587642099},
{"learn":[0.2790103807],"iteration":326,"passed_time":2.226815881,"remaining_time":4.583018618},
{"learn":[0.2786847096],"iteration":327,"passed_time":2.23397513,"remaining_time":4.576924656},
{"learn":[0.2783619552],"iteration":328,"passed_time":2.240772239,"remaining_time":4.57008563},
{"learn":[0.2779100165],"iteration":329,"passed_time":2.247580668,"remaining_time":4.563269842},
{"learn":[0.2775937481],"iteration":330,"passed_time":2.254826873,"remaining_time":4.557338906},
{"learn":[0.2772152938],"iteration":331,"passed_time":2.262670587,"remaining_time":4.552602265},
{"learn":[0.276850183],"iteration":332,"passed_time":2.269716304,"remaining_time":4.546248573},
{"learn":[0.276631431],"iteration":333,"passed_time":2.276557894,"remaining_time":4.539483704},
{"learn":[0.2763828185],"iteration":334,"passed_time":2.283320051,"remaining_time":4.532560698},
{"learn":[0.2762576137],"iteration":335,"passed_time":2.289960453,"remaining_time":4.525398039},
{"learn":[0.2760469215],"iteration":336,"passed_time":2.296777327,"remaining_time":4.518585661},
{"learn":[0.2757448569],"iteration":337,"passed_time":2.303923882,"remaining_time":4.512418965},
{"learn":[0.2756296732],"iteration":338,"passed_time":2.310379653,"remaining_time":4.504899559},
{"learn":[0.2753896684],"iteration":339,"passed_time":2.316777954,"remaining_time":4.497274853},
{"learn":[0.2749688294],"iteration":340,"passed_time":2.32353741,"remaining_time":4.490355288},
{"learn":[0.2748780095],"iteration":341,"passed_time":2.330368767,"remaining_time":4.483574997},
{"learn":[0.2745898138],"iteration":342,"passed_time":2.336715488,"remaining_time":4.475866109},
{"learn":[0.2742571839],"iteration":343,"passed_time":2.343334803,"remaining_time":4.468684974},
{"learn":[0.2740127877],"iteration":344,"passed_time":2.349583771,"remaining_time":4.46080397},
{"learn":[0.2737434995],"iteration":345,"passed_time":2.355934404,"remaining_time":4.453124567},
{"learn":[0.2735564968],"iteration":346,"passed_time":2.3623992,"remaining_time":4.445667659},
{"learn":[0.2730992719],"iteration":347,"passed_time":2.368679279,"remaining_time":4.437870374},
{"learn":[0.2729664963],"iteration":348,"passed_time":2.375093919,"remaining_time":4.430332783},
{"learn":[0.2726748637],"iteration":349,"passed_time":2.381297492,"remaining_time":4.422409629},
{"learn":[0.2725815428],"iteration":350,"passed_time":2.388048109,"remaining_time":4.415507757},
{"learn":[0.2723162345],"iteration":351,"passed_time":2.394688852,"remaining_time":4.408404478},
{"learn":[0.2718032755],"iteration":352,"passed_time":2.401316172,"remaining_time":4.401279215},
{"learn":[0.2717151877],"iteration":353,"passed_time":2.408082033,"remaining_time":4.394409586},
{"learn":[0.2715253697],"iteration":354,"passed_time":2.414697709,"remaining_time":4.387267668},
{"learn":[0.2712386625],"iteration":355,"passed_time":2.4217499,"remaining_time":4.380918358},
{"learn":[0.2710829278],"iteration":356,"passed_time":2.429361771,"remaining_time":4.375573161},
{"learn":[0.2708877051],"iteration":357,"passed_time":2.436058951,"remaining_time":4.36857499},
{"learn":[0.2706982418],"iteration":358,"passed_time":2.442794642,"remaining_time":4.361647257},
{"learn":[0.2704532055],"iteration":359,"passed_time":2.449578465,"remaining_time":4.354806159},
{"learn":[0.2701751611],"iteration":360,"passed_time":2.456390843,"remaining_time":4.348015924},
{"learn":[0.2696969801],"iteration":361,"passed_time":2.463799777,"remaining_time":4.342276955},
{"learn":[0.2693268124],"iteration":362,"passed_time":2.471298667,"remaining_time":4.336686642},
{"learn":[0.2690934994],"iteration":363,"passed_time":2.477943179,"remaining_time":4.329593028},
{"learn":[0.2689417668],"iteration":364,"passed_time":2.484772501,"remaining_time":4.322823392},
{"learn":[0.2687477656],"iteration":365,"passed_time":2.491559228,"remaining_time":4.315979646},
{"learn":[0.268621618],"iteration":366,"passed_time":2.498556065,"remaining_time":4.309498608},
{"learn":[0.2685038061],"iteration":367,"passed_time":2.505474108,"remaining_time":4.302879447},
{"learn":[0.2683376334],"iteration":368,"passed_time":2.512715435,"remaining_time":4.29681149},
{"learn":[0.2682772032],"iteration":369,"passed_time":2.519799245,"remaining_time":4.290468985},
{"learn":[0.2680446488],"iteration":370,"passed_time":2.526588856,"remaining_time":4.283623695},
{"learn":[0.26784224],"iteration":371,"passed_time":2.533125682,"remaining_time":4.276351958},
{"learn":[0.267601167],"iteration":372,"passed_time":2.539623118,"remaining_time":4.269017949},
{"learn":[0.2671638536],"iteration":373,"passed_time":2.546321393,"remaining_time":4.262024577},
{"learn":[0.2667747635],"iteration":374,"passed_time":2.553667314,"remaining_time":4.25611219},
{"learn":[0.2665713457],"iteration":375,"passed_time":2.560627355,"remaining_time":4.24955178},
{"learn":[0.2664453192],"iteration":376,"passed_time":2.567416573,"remaining_time":4.242706962},
{"learn":[0.2661006653],"iteration":377,"passed_time":2.574170142,"remaining_time":4.235803779},
{"learn":[0.265798898],"iteration":378,"passed_time":2.580781923,"remaining_time":4.228669061},
{"learn":[0.2655698984],"iteration":379,"passed_time":2.587641219,"remaining_time":4.221940936},
{"learn":[0.2652267161],"iteration":380,"passed_time":2.594302635,"remaining_time":4.214890633},
{"learn":[0.2649437886],"iteration":381,"passed_time":2.601233929,"remaining_time":4.208278974},
{"learn":[0.2647857029],"iteration":382,"passed_time":2.608093427,"remaining_time":4.201549986},
{"learn":[0.2645465008],"iteration":383,"passed_time":2.61466835,"remaining_time":4.194363812},
{"learn":[0.2642062593],"iteration":384,"passed_time":2.623494712,"remaining_time":4.190777267},
{"learn":[0.2638706874],"iteration":385,"passed_time":2.630099622,"remaining_time":4.183629968},
{"learn":[0.2635989273],"iteration":386,"passed_time":2.637028973,"remaining_time":4.176999381},
{"learn":[0.2632711058],"iteration":387,"passed_time":2.643708314,"remaining_time":4.169972907},
{"learn":[0.2630715744],"iteration":388,"passed_time":2.650673692,"remaining_time":4.163397496},
{"learn":[0.2628682087],"iteration":389,"passed_time":2.657293494,"remaining_time":4.156279568},
{"learn":[0.2626022413],"iteration":390,"passed_time":2.664541259,"remaining_time":4.150142267},
{"learn":[0.2623332748],"iteration":391,"passed_time":2.671201351,"remaining_time":4.14308781},
{"learn":[0.2621762801],"iteration":392,"passed_time":2.679424518,"remaining_time":4.138449574},
{"learn":[0.2620385037],"iteration":393,"passed_time":2.686589945,"remaining_time":4.132166261},
{"learn":[0.2616433374],"iteration":394,"passed_time":2.693507514,"remaining_time":4.12549885},
{"learn":[0.2615330126],"iteration":395,"passed_time":2.700134389,"remaining_time":4.118386795},
{"learn":[0.2611534737],"iteration":396,"passed_time":2.706803073,"remaining_time":4.111340688},
{"learn":[0.2609534498],"iteration":397,"passed_time":2.714207842,"remaining_time":4.105409851},
{"learn":[0.2606605493],"iteration":398,"passed_time":2.720744535,"remaining_time":4.098164074},
{"learn":[0.2605545916],"iteration":399,"passed_time":2.727296574,"remaining_time":4.090944861},
{"learn":[0.2604239586],"iteration":400,"passed_time":2.734245222,"remaining_time":4.084321416},
{"learn":[0.2600791635],"iteration":401,"passed_time":2.741156184,"remaining_time":4.077640294},
{"learn":[0.2599203398],"iteration":402,"passed_time":2.747917897,"remaining_time":4.070736935},
{"learn":[0.2597318598],"iteration":403,"passed_time":2.754623191,"remaining_time":4.063751043},
{"learn":[0.2594567559],"iteration":404,"passed_time":2.761343013,"remaining_time":4.056787883},
{"learn":[0.2592512138],"iteration":405,"passed_time":2.76804458,"remaining_time":4.049799213},
{"learn":[0.2590123057],"iteration":406,"passed_time":2.77480321,"remaining_time":4.042895095},
{"learn":[0.2587212653],"iteration":407,"passed_time":2.782045175,"remaining_time":4.036693},
{"learn":[0.2583139483],"iteration":408,"passed_time":2.788684439,"remaining_time":4.029614923},
{"learn":[0.2580814909],"iteration":409,"passed_time":2.795497647,"remaining_time":4.022789296},
{"learn":[0.2580011825],"iteration":410,"passed_time":2.802421005,"remaining_time":4.016121587},
{"learn":[0.2577870057],"iteration":411,"passed_time":2.80938599,"remaining_time":4.009512044},
{"learn":[0.2577097245],"iteration":412,"passed_time":2.817006379,"remaining_time":4.003832311},
{"learn":[0.2574400607],"iteration":413,"passed_time":2.825410317,"remaining_time":3.999252284},
{"learn":[0.257175631],"iteration":414,"passed_time":2.832321249,"remaining_time":3.99254923},
{"learn":[0.256826352],"iteration":415,"passed_time":2.839317239,"remaining_time":3.985964585},
{"learn":[0.2566556308],"iteration":416,"passed_time":2.84677677,"remaining_time":3.980026035},
{"learn":[0.2566136241],"iteration":417,"passed_time":2.853637669,"remaining_time":3.973246707},
{"learn":[0.2564448198],"iteration":418,"passed_time":2.860850053,"remaining_time":3.966954369},
{"learn":[0.2560233922],"iteration":419,"passed_time":2.86905804,"remaining_time":3.962032531},
{"learn":[0.2558007866],"iteration":420,"passed_time":2.877343241,"remaining_time":3.957201275},
{"learn":[0.2555055986],"iteration":421,"passed_time":2.884845778,"remaining_time":3.951281658},
{"learn":[0.2553692447],"iteration":422,"passed_time":2.893393341,"remaining_time":3.946780042},
{"learn":[0.2551508605],"iteration":423,"passed_time":2.901708221,"remaining_time":3.941943244},
{"learn":[0.2550390518],"iteration":424,"passed_time":2.909025773,"remaining_time":3.935740751},
{"learn":[0.2549265836],"iteration":425,"passed_time":2.915751469,"remaining_time":3.928735547},
{"learn":[0.2547261044],"iteration":426,"passed_time":2.922631651,"remaining_time":3.92193896},
{"learn":[0.2545399086],"iteration":427,"passed_time":2.929152248,"remaining_time":3.914661415},
{"learn":[0.2544107317],"iteration":428,"passed_time":2.935983422,"remaining_time":3.907800778},
{"learn":[0.2542155705],"iteration":429,"passed_time":2.94243528,"remaining_time":3.900437464},
{"learn":[0.2539968705],"iteration":430,"passed_time":2.949069839,"remaining_time":3.893319579},
{"learn":[0.253772787],"iteration":431,"passed_time":2.955797942,"remaining_time":3.886326924},
{"learn":[0.2534859634],"iteration":432,"passed_time":2.962427292,"remaining_time":3.879206177},
{"learn":[0.2533985606],"iteration":433,"passed_time":2.969122191,"remaining_time":3.87217318},
{"learn":[0.2529041324],"iteration":434,"passed_time":2.975626468,"remaining_time":3.864894148},
{"learn":[0.2525791632],"iteration":435,"passed_time":2.982331988,"remaining_time":3.857878994},
{"learn":[0.2524545173],"iteration":436,"passed_time":2.988874779,"remaining_time":3.850655608},
{"learn":[0.252336176],"iteration":437,"passed_time":2.995669455,"remaining_time":3.843758524},
{"learn":[0.2519888627],"iteration":438,"passed_time":3.002217836,"remaining_time":3.836547166},
{"learn":[0.2515955452],"iteration":439,"passed_time":3.008686935,"remaining_time":3.829237918},
{"learn":[0.2513030049],"iteration":440,"passed_time":3.015136983,"remaining_time":3.82190833},
{"learn":[0.2512013027],"iteration":441,"passed_time":3.021932755,"remaining_time":3.81501918},
{"learn":[0.2510271853],"iteration":442,"passed_time":3.030188784,"remaining_time":3.809966485},
{"learn":[0.2508069169],"iteration":443,"passed_time":3.036853528,"remaining_time":3.80290667},
{"learn":[0.2506525727],"iteration":444,"passed_time":3.043709089,"remaining_time":3.796086616},
{"learn":[0.2503005214],"iteration":445,"passed_time":3.050342436,"remaining_time":3.788990381},
{"learn":[0.2501154027],"iteration":446,"passed_time":3.057246923,"remaining_time":3.782231652},
{"learn":[0.2499625181],"iteration":447,"passed_time":3.063947754,"remaining_time":3.77522134},
{"learn":[0.2497921185],"iteration":448,"passed_time":3.070815565,"remaining_time":3.768417319},
{"learn":[0.2495219083],"iteration":449,"passed_time":3.077188583,"remaining_time":3.761008268},
{"learn":[0.249276939],"iteration":450,"passed_time":3.083670442,"remaining_time":3.753736303},
{"learn":[0.2491550264],"iteration":451,"passed_time":3.09032719,"remaining_time":3.746679867},
{"learn":[0.2489725123],"iteration":452,"passed_time":3.097066381,"remaining_time":3.739724747},
{"learn":[0.2488468531],"iteration":453,"passed_time":3.105096304,"remaining_time":3.734322868},
{"learn":[0.2487355897],"iteration":454,"passed_time":3.112113007,"remaining_time":3.7276958},
{"learn":[0.248681538],"iteration":455,"passed_time":3.118816125,"remaining_time":3.720692921},
{"learn":[0.2485626336],"iteration":456,"passed_time":3.125402908,"remaining_time":3.713553127},
{"learn":[0.2482974101],"iteration":457,"passed_time":3.132493405,"remaining_time":3.707011847},
{"learn":[0.248087857],"iteration":458,"passed_time":3.139074439,"remaining_time":3.699867694},
{"learn":[0.247774408],"iteration":459,"passed_time":3.145690568,"remaining_time":3.692767188},
{"learn":[0.2475769386],"iteration":460,"passed_time":3.152201144,"remaining_time":3.685545373},
{"learn":[0.2473549742],"iteration":461,"passed_time":3.158818627,"remaining_time":3.678451128},
{"learn":[0.2473276348],"iteration":462,"passed_time":3.165517589,"remaining_time":3.671453445},
{"learn":[0.2471379965],"iteration":463,"passed_time":3.172172091,"remaining_time":3.664405691},
{"learn":[0.2470406816],"iteration":464,"passed_time":3.179494891,"remaining_time":3.65812853},
{"learn":[0.2470189706],"iteration":465,"passed_time":3.186289271,"remaining_time":3.651241354},
{"learn":[0.2469042641],"iteration":466,"passed_time":3.192806719,"remaining_time":3.644038504},
{"learn":[0.2468010431],"iteration":467,"passed_time":3.199602049,"remaining_time":3.637154466},
{"learn":[0.2466723485],"iteration":468,"passed_time":3.206528958,"remaining_time":3.630419779},
{"learn":[0.246514584],"iteration":469,"passed_time":3.213270695,"remaining_time":3.623475464},
{"learn":[0.2463501832],"iteration":470,"passed_time":3.220361809,"remaining_time":3.616924409},
{"learn":[0.2461742654],"iteration":471,"passed_time":3.227350885,"remaining_time":3.610256922},
{"learn":[0.245762722],"iteration":472,"passed_time":3.236070342,"remaining_time":3.605516005},
{"learn":[0.2455648672],"iteration":473,"passed_time":3.242696032,"remaining_time":3.598434837},
{"learn":[0.2454781],"iteration":474,"passed_time":3.249513814,"remaining_time":3.5915679},
{"learn":[0.2452549241],"iteration":475,"passed_time":3.256239784,"remaining_time":3.584600098},
{"learn":[0.2450562239],"iteration":476,"passed_time":3.263179673,"remaining_time":3.57786786},
{"learn":[0.244832196],"iteration":477,"passed_time":3.27015114,"remaining_time":3.571169237},
{"learn":[0.2445991438],"iteration":478,"passed_time":3.277133536,"remaining_time":3.564481361},
{"learn":[0.2444183065],"iteration":479,"passed_time":3.284053862,"remaining_time":3.557725017},
{"learn":[0.2442253173],"iteration":480,"passed_time":3.290544255,"remaining_time":3.550504092},
{"learn":[0.2440429603],"iteration":481,"passed_time":3.297478234,"remaining_time":3.543762916},
{"learn":[0.2438604716],"iteration":482,"passed_time":3.304222469,"remaining_time":3.53681784},
{"learn":[0.2437627355],"iteration":483,"passed_time":3.311516951,"remaining_time":3.53046022},
{"learn":[0.2436742321],"iteration":484,"passed_time":3.319629564,"remaining_time":3.524967475},
{"learn":[0.2435284659],"iteration":485,"passed_time":3.32637542,"remaining_time":3.518018448},
{"learn":[0.2435131725],"iteration":486,"passed_time":3.33356936,"remaining_time":3.511542263},
{"learn":[0.2433853021],"iteration":487,"passed_time":3.340713161,"remaining_time":3.50501053},
{"learn":[0.2431591898],"iteration":488,"passed_time":3.347418398,"remaining_time":3.498017999},
{"learn":[0.2429913531],"iteration":489,"passed_time":3.354220957,"remaining_time":3.491127935},
{"learn":[0.2429255324],"iteration":490,"passed_time":3.36125865,"remaining_time":3.484481981},
{"learn":[0.2428473769],"iteration":491,"passed_time":3.367799594,"remaining_time":3.477321532},
{"learn":[0.2426558939],"iteration":492,"passed_time":3.374538865,"remaining_time":3.470367555},
{"learn":[0.2425458462],"iteration":493,"passed_time":3.380994984,"remaining_time":3.463124416},
{"learn":[0.2422622051],"iteration":494,"passed_time":3.387906208,"remaining_time":3.456348758},
{"learn":[0.2422250625],"iteration":495,"passed_time":3.394713798,"remaining_time":3.449467246},
{"learn":[0.2418932994],"iteration":496,"passed_time":3.401525088,"remaining_time":3.442589777},
{"learn":[0.2417287804],"iteration":497,"passed_time":3.408048243,"remaining_time":3.435422124},
{"learn":[0.2415864946],"iteration":498,"passed_time":3.415153043,"remaining_time":3.428841031},
{"learn":[0.2414752364],"iteration":499,"passed_time":3.422184379,"remaining_time":3.422184379},
{"learn":[0.2413674737],"iteration":500,"passed_time":3.429331349,"remaining_time":3.415641403},
{"learn":[0.241310268],"iteration":501,"passed_time":3.437376416,"remaining_time":3.409986962},
{"learn":[0.2411268655],"iteration":502,"passed_time":3.444100371,"remaining_time":3.403017663},
{"learn":[0.2409480011],"iteration":503,"passed_time":3.451250177,"remaining_time":3.396468428},
{"learn":[0.2408559075],"iteration":504,"passed_time":3.458484231,"remaining_time":3.389999395},
{"learn":[0.2407897905],"iteration":505,"passed_time":3.46530591,"remaining_time":3.383124742},
{"learn":[0.2406456523],"iteration":506,"passed_time":3.472099534,"remaining_time":3.376223018},
{"learn":[0.2404847101],"iteration":507,"passed_time":3.478802647,"remaining_time":3.36923406},
{"learn":[0.240352758],"iteration":508,"passed_time":3.485540778,"remaining_time":3.362280004},
{"learn":[0.2401675579],"iteration":509,"passed_time":3.49232455,"remaining_time":3.355370647},
{"learn":[0.2399157757],"iteration":510,"passed_time":3.499109812,"remaining_time":3.348463206},
{"learn":[0.2398636746],"iteration":511,"passed_time":3.50584338,"remaining_time":3.341506971},
{"learn":[0.2396471766],"iteration":512,"passed_time":3.512783017,"remaining_time":3.334747231},
{"learn":[0.2393937587],"iteration":513,"passed_time":3.519647014,"remaining_time":3.32791527},
{"learn":[0.2393241999],"iteration":514,"passed_time":3.527062295,"remaining_time":3.321602355},
{"learn":[0.2391593731],"iteration":515,"passed_time":3.535508142,"remaining_time":3.316251823},
{"learn":[0.2389638875],"iteration":516,"passed_time":3.542238621,"remaining_time":3.309286758},
{"learn":[0.238775539],"iteration":517,"passed_time":3.549272525,"remaining_time":3.302604937},
{"learn":[0.238519364],"iteration":518,"passed_time":3.556056482,"remaining_time":3.295690111},
{"learn":[0.2382398312],"iteration":519,"passed_time":3.562739678,"remaining_time":3.28868278},
{"learn":[0.2379872764],"iteration":520,"passed_time":3.570131696,"remaining_time":3.282328373},
{"learn":[0.2377311368],"iteration":521,"passed_time":3.577360154,"remaining_time":3.275820218},
{"learn":[0.2375087799],"iteration":522,"passed_time":3.584448079,"remaining_time":3.269181135},
{"learn":[0.237138648],"iteration":523,"passed_time":3.59147709,"remaining_time":3.262486822},
{"learn":[0.2370085385],"iteration":524,"passed_time":3.598509205,"remaining_time":3.255794043},
{"learn":[0.2368697246],"iteration":525,"passed_time":3.605243898,"remaining_time":3.248831953},
{"learn":[0.2367446427],"iteration":526,"passed_time":3.611965233,"remaining_time":3.241858738},
{"learn":[0.2365489011],"iteration":527,"passed_time":3.618666077,"remaining_time":3.23486816},
{"learn":[0.2363137938],"iteration":528,"passed_time":3.625340582,"remaining_time":3.227855225},
{"learn":[0.2360816401],"iteration":529,"passed_time":3.63224644,"remaining_time":3.22104873},
{"learn":[0.2357487023],"iteration":530,"passed_time":3.640537859,"remaining_time":3.215465642},
{"learn":[0.2354729098],"iteration":531,"passed_time":3.647228862,"remaining_time":3.208464488},
{"learn":[0.2352916249],"iteration":532,"passed_time":3.653724494,"remaining_time":3.201293319},
{"learn":[0.2349160734],"iteration":533,"passed_time":3.660865763,"remaining_time":3.1946881},
{"learn":[0.2347942747],"iteration":534,"passed_time":3.667625565,"remaining_time":3.187749323},
{"learn":[0.2346267737],"iteration":535,"passed_time":3.674476427,"remaining_time":3.180890042},
{"learn":[0.2343670869],"iteration":536,"passed_time":3.681322404,"remaining_time":3.174026579},
{"learn":[0.2343033751],"iteration":537,"passed_time":3.687777619,"remaining_time":3.16682762},
{"learn":[0.2341315531],"iteration":538,"passed_time":3.694483541,"remaining_time":3.159845849},
{"learn":[0.2340015887],"iteration":539,"passed_time":3.701292034,"remaining_time":3.152952473},
{"learn":[0.2339415877],"iteration":540,"passed_time":3.707775919,"remaining_time":3.145784005},
{"learn":[0.2336848588],"iteration":541,"passed_time":3.714189219,"remaining_time":3.138558417},
{"learn":[0.2335357125],"iteration":542,"passed_time":3.720939015,"remaining_time":3.131619024},
{"learn":[0.2333534532],"iteration":543,"passed_time":3.727358057,"remaining_time":3.124403077},
{"learn":[0.2330929049],"iteration":544,"passed_time":3.734127258,"remaining_time":3.11748239},
{"learn":[0.2330054066],"iteration":545,"passed_time":3.742238605,"remaining_time":3.111678254},
{"learn":[0.2329156209],"iteration":546,"passed_time":3.748969985,"remaining_time":3.104722858},
{"learn":[0.2328365489],"iteration":547,"passed_time":3.755804935,"remaining_time":3.097853705},
{"learn":[0.2327704769],"iteration":548,"passed_time":3.76261157,"remaining_time":3.090961417},
{"learn":[0.2325882525],"iteration":549,"passed_time":3.769182991,"remaining_time":3.083876993},
{"learn":[0.2322650182],"iteration":550,"passed_time":3.775913697,"remaining_time":3.076924229},
{"learn":[0.2321792417],"iteration":551,"passed_time":3.782535618,"remaining_time":3.06988398},
{"learn":[0.2321237663],"iteration":552,"passed_time":3.789104711,"remaining_time":3.062802542},
{"learn":[0.2320173313],"iteration":553,"passed_time":3.795888664,"remaining_time":3.055895928},
{"learn":[0.231831033],"iteration":554,"passed_time":3.802546781,"remaining_time":3.04888886},
{"learn":[0.23161618],"iteration":555,"passed_time":3.809364285,"remaining_time":3.042010329},
{"learn":[0.2313452024],"iteration":556,"passed_time":3.81649389,"remaining_time":3.035380239},
{"learn":[0.2312275758],"iteration":557,"passed_time":3.82297379,"remaining_time":3.028233719},
{"learn":[0.2309009984],"iteration":558,"passed_time":3.829555859,"remaining_time":3.021170186},
{"learn":[0.2307005227],"iteration":559,"passed_time":3.836283503,"remaining_time":3.014222753},
{"learn":[0.2305681447],"iteration":560,"passed_time":3.843999363,"remaining_time":3.008049412},
{"learn":[0.2304177036],"iteration":561,"passed_time":3.851279861,"remaining_time":3.00153128},
{"learn":[0.2302795904],"iteration":562,"passed_time":3.85815152,"remaining_time":2.994693098},
{"learn":[0.2299617797],"iteration":563,"passed_time":3.864657047,"remaining_time":2.98757176},
{"learn":[0.2298634782],"iteration":564,"passed_time":3.871496932,"remaining_time":2.980710028},
{"learn":[0.2297074506],"iteration":565,"passed_time":3.878833791,"remaining_time":2.974229444},
{"learn":[0.2295241748],"iteration":566,"passed_time":3.886191425,"remaining_time":2.967761705},
{"learn":[0.2292239646],"iteration":567,"passed_time":3.89423248,"remaining_time":2.961810619},
{"learn":[0.2291566794],"iteration":568,"passed_time":3.901878779,"remaining_time":2.95555317},
{"learn":[0.2290076695],"iteration":569,"passed_time":3.909426481,"remaining_time":2.949216468},
{"learn":[0.2288857564],"iteration":570,"passed_time":3.917374404,"remaining_time":2.943176216},
{"learn":[0.228782256],"iteration":571,"passed_time":3.923886107,"remaining_time":2.936054639},
{"learn":[0.2287393279],"iteration":572,"passed_time":3.930519712,"remaining_time":2.929026033},
{"learn":[0.2283862707],"iteration":573,"passed_time":3.937316749,"remaining_time":2.922120096},
{"learn":[0.2282242727],"iteration":574,"passed_time":3.943656404,"remaining_time":2.914876473},
{"learn":[0.2280561826],"iteration":575,"passed_time":3.950523121,"remaining_time":2.908023964},
{"learn":[0.2277879716],"iteration":576,"passed_time":3.957601183,"remaining_time":2.901326344},
{"learn":[0.2274850243],"iteration":577,"passed_time":3.96410543,"remaining_time":2.894208463},
{"learn":[0.227402014],"iteration":578,"passed_time":3.970653121,"remaining_time":2.88712429},
{"learn":[0.2272386031],"iteration":579,"passed_time":3.977050702,"remaining_time":2.879933267},
{"learn":[0.2269906711],"iteration":580,"passed_time":3.983527969,"remaining_time":2.872802443},
{"learn":[0.2268592344],"iteration":581,"passed_time":3.989832609,"remaining_time":2.865549881},
{"learn":[0.226653193],"iteration":582,"passed_time":3.996173919,"remaining_time":2.8583268},
{"learn":[0.2265574892],"iteration":583,"passed_time":4.00255013,"remaining_time":2.851131599},
{"learn":[0.2263789816],"iteration":584,"passed_time":4.00936108,"remaining_time":2.844247604},
{"learn":[0.2261375516],"iteration":585,"passed_time":4.015622299,"remaining_time":2.836975481},
{"learn":[0.2259814935],"iteration":586,"passed_time":4.02233227,"remaining_time":2.830022534},
{"learn":[0.2258009235],"iteration":587,"passed_time":4.02898241,"remaining_time":2.823028491},
{"learn":[0.2256449205],"iteration":588,"passed_time":4.035691188,"remaining_time":2.816076533},
{"learn":[0.225593683],"iteration":589,"passed_time":4.042724283,"remaining_time":2.809350773},
{"learn":[0.2254902581],"iteration":590,"passed_time":4.05116217,"remaining_time":2.803596155},
{"learn":[0.2253001137],"iteration":591,"passed_time":4.058421867,"remaining_time":2.797020476},
{"learn":[0.2250821338],"iteration":592,"passed_time":4.065602383,"remaining_time":2.790388145},
{"learn":[0.2248728068],"iteration":593,"passed_time":4.072470474,"remaining_time":2.783540425},
{"learn":[0.2246929225],"iteration":594,"passed_time":4.078980762,"remaining_time":2.77644909},
{"learn":[0.2244857735],"iteration":595,"passed_time":4.085834432,"remaining_time":2.769592467},
{"learn":[0.2242415758],"iteration":596,"passed_time":4.092137648,"remaining_time":2.762364275},
{"learn":[0.2240639234],"iteration":597,"passed_time":4.099167762,"remaining_time":2.755627827},
{"learn":[0.2238013421],"iteration":598,"passed_time":4.105896516,"remaining_time":2.748688653},
{"learn":[0.2236238369],"iteration":599,"passed_time":4.112611423,"remaining_time":2.741740949},
{"learn":[0.223272683],"iteration":600,"passed_time":4.119385048,"remaining_time":2.734833002},
{"learn":[0.2229801042],"iteration":601,"passed_time":4.126065383,"remaining_time":2.727863825},
{"learn":[0.222703743],"iteration":602,"passed_time":4.132704453,"remaining_time":2.720868438},
{"learn":[0.222566546],"iteration":603,"passed_time":4.139130031,"remaining_time":2.713734259},
{"learn":[0.2224064228],"iteration":604,"passed_time":4.146102735,"remaining_time":2.706959637},
{"learn":[0.2222841713],"iteration":605,"passed_time":4.152664892,"remaining_time":2.699917438},
{"learn":[0.2221541101],"iteration":606,"passed_time":4.159562878,"remaining_time":2.693094252},
{"learn":[0.222147826],"iteration":607,"passed_time":4.166362323,"remaining_time":2.686207287},
{"learn":[0.2220667341],"iteration":608,"passed_time":4.172870815,"remaining_time":2.679133807},
{"learn":[0.2219345795],"iteration":609,"passed_time":4.179759582,"remaining_time":2.672305306},
{"learn":[0.2218660204],"iteration":610,"passed_time":4.186860549,"remaining_time":2.665611708},
{"learn":[0.2218004756],"iteration":611,"passed_time":4.193618728,"remaining_time":2.658699455},
{"learn":[0.2215670956],"iteration":612,"passed_time":4.200390352,"remaining_time":2.651796193},
{"learn":[0.2214698289],"iteration":613,"passed_time":4.206910344,"remaining_time":2.644735168},
{"learn":[0.2212430371],"iteration":614,"passed_time":4.213729495,"remaining_time":2.63786318},
{"learn":[0.2211124998],"iteration":615,"passed_time":4.220636373,"remaining_time":2.631046051},
{"learn":[0.2209654364],"iteration":616,"passed_time":4.227232161,"remaining_time":2.624035523},
{"learn":[0.2208506566],"iteration":617,"passed_time":4.234059354,"remaining_time":2.617169374},
{"learn":[0.2207523609],"iteration":618,"passed_time":4.240750132,"remaining_time":2.610219387},
{"learn":[0.2206345563],"iteration":619,"passed_time":4.248007875,"remaining_time":2.60361773},
{"learn":[0.2203921107],"iteration":620,"passed_time":4.255408747,"remaining_time":2.597101312},
{"learn":[0.2203047617],"iteration":621,"passed_time":4.262314861,"remaining_time":2.590281378},
{"learn":[0.2202434368],"iteration":622,"passed_time":4.269808744,"remaining_time":2.583816848},
{"learn":[0.220042898],"iteration":623,"passed_time":4.27707824,"remaining_time":2.577213811},
{"learn":[0.2199402795],"iteration":624,"passed_time":4.283888507,"remaining_time":2.570333104},
{"learn":[0.2198064999],"iteration":625,"passed_time":4.290751296,"remaining_time":2.563484001},
{"learn":[0.2196377079],"iteration":626,"passed_time":4.29769995,"remaining_time":2.556685935},
{"learn":[0.2194926059],"iteration":627,"passed_time":4.304636601,"remaining_time":2.549880279},
{"learn":[0.2194268642],"iteration":628,"passed_time":4.311460261,"remaining_time":2.543007562},
{"learn":[0.2193510874],"iteration":629,"passed_time":4.318212834,"remaining_time":2.536093252},
{"learn":[0.2191080266],"iteration":630,"passed_time":4.324896316,"remaining_time":2.52913905},
{"learn":[0.2190344378],"iteration":631,"passed_time":4.33153612,"remaining_time":2.522160272},
{"learn":[0.2188800806],"iteration":632,"passed_time":4.338446438,"remaining_time":2.515339404},
{"learn":[0.2186371448],"iteration":633,"passed_time":4.344990517,"remaining_time":2.508306829},
{"learn":[0.2185366367],"iteration":634,"passed_time":4.351511568,"remaining_time":2.501262555},
{"learn":[0.2183844138],"iteration":635,"passed_time":4.358438363,"remaining_time":2.494452145},
{"learn":[0.2180644303],"iteration":636,"passed_time":4.365064273,"remaining_time":2.487469908},
{"learn":[0.2179167362],"iteration":637,"passed_time":4.372231164,"remaining_time":2.480795739},
{"learn":[0.2178399157],"iteration":638,"passed_time":4.37887256,"remaining_time":2.473823152},
{"learn":[0.2176613946],"iteration":639,"passed_time":4.386012277,"remaining_time":2.467131906},
{"learn":[0.217404425],"iteration":640,"passed_time":4.392572553,"remaining_time":2.460114737},
{"learn":[0.2172924009],"iteration":641,"passed_time":4.399269237,"remaining_time":2.453175057},
{"learn":[0.2171861251],"iteration":642,"passed_time":4.405761854,"remaining_time":2.446122833},
{"learn":[0.2170113233],"iteration":643,"passed_time":4.412057999,"remaining_time":2.438963738},
{"learn":[0.2169445316],"iteration":644,"passed_time":4.418511366,"remaining_time":2.431893852},
{"learn":[0.2167864921],"iteration":645,"passed_time":4.424901328,"remaining_time":2.42479113},
{"learn":[0.2166117979],"iteration":646,"passed_time":4.431491976,"remaining_time":2.417800104},
{"learn":[0.2165762226],"iteration":647,"passed_time":4.43822559,"remaining_time":2.410887975},
{"learn":[0.2163744076],"iteration":648,"passed_time":4.446174335,"remaining_time":2.404633577},
{"learn":[0.2163237274],"iteration":649,"passed_time":4.454182196,"remaining_time":2.398405798},
{"learn":[0.2162603718],"iteration":650,"passed_time":4.460801148,"remaining_time":2.391427958},
{"learn":[0.216103782],"iteration":651,"passed_time":4.467694693,"remaining_time":2.384597781},
{"learn":[0.2160235823],"iteration":652,"passed_time":4.474657649,"remaining_time":2.377804294},
{"learn":[0.2159995469],"iteration":653,"passed_time":4.481500033,"remaining_time":2.3709465},
{"learn":[0.2159199224],"iteration":654,"passed_time":4.488899517,"remaining_time":2.364382188},
{"learn":[0.2158110945],"iteration":655,"passed_time":4.495612658,"remaining_time":2.357455418},
{"learn":[0.2156992107],"iteration":656,"passed_time":4.502651467,"remaining_time":2.35069932},
{"learn":[0.2155377347],"iteration":657,"passed_time":4.508976098,"remaining_time":2.343571163},
{"learn":[0.2152333112],"iteration":658,"passed_time":4.515376447,"remaining_time":2.336484626},
{"learn":[0.2151501712],"iteration":659,"passed_time":4.522183546,"remaining_time":2.329609705},
{"learn":[0.2150627081],"iteration":660,"passed_time":4.528753174,"remaining_time":2.322613201},
{"learn":[0.2148896575],"iteration":661,"passed_time":4.535283653,"remaining_time":2.315597998},
{"learn":[0.2147284629],"iteration":662,"passed_time":4.542585931,"remaining_time":2.308976559},
{"learn":[0.2146206992],"iteration":663,"passed_time":4.549732258,"remaining_time":2.302274154},
{"learn":[0.214507965],"iteration":664,"passed_time":4.557118805,"remaining_time":2.295691428},
{"learn":[0.2143845785],"iteration":665,"passed_time":4.563497833,"remaining_time":2.288601015},
{"learn":[0.2142573218],"iteration":666,"passed_time":4.570249309,"remaining_time":2.281698681},
{"learn":[0.214186476],"iteration":667,"passed_time":4.576544072,"remaining_time":2.274569808},
{"learn":[0.2140252607],"iteration":668,"passed_time":4.583000936,"remaining_time":2.267523632},
{"learn":[0.2139252126],"iteration":669,"passed_time":4.58955146,"remaining_time":2.260525346},
{"learn":[0.2138671037],"iteration":670,"passed_time":4.596083836,"remaining_time":2.253519496},
{"learn":[0.2136808392],"iteration":671,"passed_time":4.602444005,"remaining_time":2.246431002},
{"learn":[0.2134212632],"iteration":672,"passed_time":4.608768408,"remaining_time":2.239327295},
{"learn":[0.2132527418],"iteration":673,"passed_time":4.614973393,"remaining_time":2.23216814},
{"learn":[0.2131236988],"iteration":674,"passed_time":4.621406021,"remaining_time":2.225121418},
{"learn":[0.2129822716],"iteration":675,"passed_time":4.628556302,"remaining_time":2.218420476},
{"learn":[0.2127390607],"iteration":676,"passed_time":4.635132371,"remaining_time":2.211444248},
{"learn":[0.2126854177],"iteration":677,"passed_time":4.642904476,"remaining_time":2.205037229},
{"learn":[0.2126133481],"iteration":678,"passed_time":4.650331548,"remaining_time":2.198463073},
{"learn":[0.2124020571],"iteration":679,"passed_time":4.656976692,"remaining_time":2.191518443},
{"learn":[0.2123415122],"iteration":680,"passed_time":4.664020246,"remaining_time":2.184761319},
{"learn":[0.2122749064],"iteration":681,"passed_time":4.6705226,"remaining_time":2.177751007},
{"learn":[0.212254735],"iteration":682,"passed_time":4.677420559,"remaining_time":2.170925794},
{"learn":[0.2121664405],"iteration":683,"passed_time":4.684364147,"remaining_time":2.164121448},
{"learn":[0.2120150224],"iteration":684,"passed_time":4.691765665,"remaining_time":2.157527277},
{"learn":[0.2116504891],"iteration":685,"passed_time":4.699019087,"remaining_time":2.150862964},
{"learn":[0.2115910075],"iteration":686,"passed_time":4.705639414,"remaining_time":2.143908496},
{"learn":[0.2114991149],"iteration":687,"passed_time":4.712389726,"remaining_time":2.137013946},
{"learn":[0.2112280324],"iteration":688,"passed_time":4.719256281,"remaining_time":2.130172284},
{"learn":[0.2111739781],"iteration":689,"passed_time":4.725889166,"remaining_time":2.123225568},
{"learn":[0.2109796467],"iteration":690,"passed_time":4.732441836,"remaining_time":2.116243889},
{"learn":[0.210836898],"iteration":691,"passed_time":4.739095875,"remaining_time":2.109308569},
{"learn":[0.2106982159],"iteration":692,"passed_time":4.745951639,"remaining_time":2.102463425},
{"learn":[0.2104944831],"iteration":693,"passed_time":4.752543723,"remaining_time":2.095501987},
{"learn":[0.2104373473],"iteration":694,"passed_time":4.759064399,"remaining_time":2.088510276},
{"learn":[0.2102726151],"iteration":695,"passed_time":4.765740863,"remaining_time":2.081587963},
{"learn":[0.2101229206],"iteration":696,"passed_time":4.772580728,"remaining_time":2.07473739},
{"learn":[0.2100663753],"iteration":697,"passed_time":4.779659004,"remaining_time":2.067989999},
{"learn":[0.2100339059],"iteration":698,"passed_time":4.786187931,"remaining_time":2.061005103},
{"learn":[0.2098346313],"iteration":699,"passed_time":4.793016144,"remaining_time":2.054149776},
{"learn":[0.2097890425],"iteration":700,"passed_time":4.799647754,"remaining_time":2.047210668},
{"learn":[0.2095961489],"iteration":701,"passed_time":4.807035922,"remaining_time":2.040593596},
{"learn":[0.2094450131],"iteration":702,"passed_time":4.814148542,"remaining_time":2.033857919},
{"learn":[0.2093855239],"iteration":703,"passed_time":4.821006154,"remaining_time":2.027013951},
{"learn":[0.2093332849],"iteration":704,"passed_time":4.827781139,"remaining_time":2.02013537},
{"learn":[0.2092413587],"iteration":705,"passed_time":4.834468413,"remaining_time":2.013220557},
{"learn":[0.2091983886],"iteration":706,"passed_time":4.841806397,"remaining_time":2.00657606},
{"learn":[0.2090902594],"iteration":707,"passed_time":4.850912705,"remaining_time":2.000658912},
{"learn":[0.2089590664],"iteration":708,"passed_time":4.857903838,"remaining_time":1.993864622},
{"learn":[0.2088044878],"iteration":709,"passed_time":4.864477949,"remaining_time":1.986899444},
{"learn":[0.2087332939],"iteration":710,"passed_time":4.87242937,"remaining_time":1.980495201},
{"learn":[0.2084471118],"iteration":711,"passed_time":4.879181938,"remaining_time":1.973601683},
{"learn":[0.2083417303],"iteration":712,"passed_time":4.886759603,"remaining_time":1.967040682},
{"learn":[0.208245869],"iteration":713,"passed_time":4.894051111,"remaining_time":1.96036221},
{"learn":[0.2080673481],"iteration":714,"passed_time":4.902576077,"remaining_time":1.954173681},
{"learn":[0.2079514741],"iteration":715,"passed_time":4.91065244,"remaining_time":1.947800688},
{"learn":[0.2079222803],"iteration":716,"passed_time":4.918276086,"remaining_time":1.941244257},
{"learn":[0.2078817858],"iteration":717,"passed_time":4.926213058,"remaining_time":1.934807914},
{"learn":[0.2078534401],"iteration":718,"passed_time":4.933671752,"remaining_time":1.928180476},
{"learn":[0.2077643245],"iteration":719,"passed_time":4.940421076,"remaining_time":1.921274863},
{"learn":[0.207713946],"iteration":720,"passed_time":4.947096119,"remaining_time":1.914340939},
{"learn":[0.2076029558],"iteration":721,"passed_time":4.953721094,"remaining_time":1.907388455},
{"learn":[0.2075165981],"iteration":722,"passed_time":4.960295268,"remaining_time":1.900417412},
{"learn":[0.2074232732],"iteration":723,"passed_time":4.967067396,"remaining_time":1.89352293},
{"learn":[0.2073447827],"iteration":724,"passed_time":4.973851727,"remaining_time":1.886633414},
{"learn":[0.2072162026],"iteration":725,"passed_time":4.980468566,"remaining_time":1.879680974},
{"learn":[0.2071387358],"iteration":726,"passed_time":4.987194673,"remaining_time":1.872770489},
{"learn":[0.2070330889],"iteration":727,"passed_time":4.993688559,"remaining_time":1.865773747},
{"learn":[0.2069413776],"iteration":728,"passed_time":5.000119514,"remaining_time":1.858754991},
{"learn":[0.2068834716],"iteration":729,"passed_time":5.006808257,"remaining_time":1.851833191},
{"learn":[0.2066478159],"iteration":730,"passed_time":5.013157064,"remaining_time":1.844786936},
{"learn":[0.2065703863],"iteration":731,"passed_time":5.01963843,"remaining_time":1.837791119},
{"learn":[0.206492821],"iteration":732,"passed_time":5.026196225,"remaining_time":1.830824546},
{"learn":[0.206454876],"iteration":733,"passed_time":5.032622072,"remaining_time":1.823811269},
{"learn":[0.2063473359],"iteration":734,"passed_time":5.039217874,"remaining_time":1.816860866},
{"learn":[0.20622765],"iteration":735,"passed_time":5.045830212,"remaining_time":1.809917359},
{"learn":[0.2060298303],"iteration":736,"passed_time":5.054014402,"remaining_time":1.803535668},
{"learn":[0.2058600074],"iteration":737,"passed_time":5.060836758,"remaining_time":1.796665624},
{"learn":[0.2056204414],"iteration":738,"passed_time":5.067854784,"remaining_time":1.789864815},
{"learn":[0.2054258166],"iteration":739,"passed_time":5.074484675,"remaining_time":1.782927048},
{"learn":[0.2053625365],"iteration":740,"passed_time":5.08167753,"remaining_time":1.776186883},
{"learn":[0.2053416208],"iteration":741,"passed_time":5.088175344,"remaining_time":1.769203826},
{"learn":[0.2052754501],"iteration":742,"passed_time":5.095081091,"remaining_time":1.762363177},
{"learn":[0.2051554244],"iteration":743,"passed_time":5.101801229,"remaining_time":1.755458487},
{"learn":[0.2050940574],"iteration":744,"passed_time":5.108462942,"remaining_time":1.748534296},
{"learn":[0.2049298132],"iteration":745,"passed_time":5.116369969,"remaining_time":1.742034815},
{"learn":[0.2049098815],"iteration":746,"passed_time":5.123016729,"remaining_time":1.735104729},
{"learn":[0.2048665009],"iteration":747,"passed_time":5.129893864,"remaining_time":1.728253013},
{"learn":[0.2048424284],"iteration":748,"passed_time":5.136845992,"remaining_time":1.72142636},
{"learn":[0.2045862882],"iteration":749,"passed_time":5.143928717,"remaining_time":1.714642906},
{"learn":[0.2045372877],"iteration":750,"passed_time":5.150823527,"remaining_time":1.707796349},
{"learn":[0.2045017202],"iteration":751,"passed_time":5.157342834,"remaining_time":1.700825828},
{"learn":[0.2044389583],"iteration":752,"passed_time":5.164306072,"remaining_time":1.694002125},
{"learn":[0.2042001424],"iteration":753,"passed_time":5.171644064,"remaining_time":1.687300318},
{"learn":[0.2040291233],"iteration":754,"passed_time":5.178298582,"remaining_time":1.680375036},
{"learn":[0.2039884032],"iteration":755,"passed_time":5.185318888,"remaining_time":1.67356853},
{"learn":[0.2038106694],"iteration":756,"passed_time":5.192153239,"remaining_time":1.666701766},
{"learn":[0.2036617324],"iteration":757,"passed_time":5.198729193,"remaining_time":1.659752592},
{"learn":[0.2035635863],"iteration":758,"passed_time":5.205414718,"remaining_time":1.652839192},
{"learn":[0.203342432],"iteration":759,"passed_time":5.212108924,"remaining_time":1.645929134},
{"learn":[0.2031960099],"iteration":760,"passed_time":5.219052249,"remaining_time":1.639097881},
{"learn":[0.2030624759],"iteration":761,"passed_time":5.225710255,"remaining_time":1.632177219},
{"learn":[0.2029798634],"iteration":762,"passed_time":5.232436117,"remaining_time":1.625278322},
{"learn":[0.202886939],"iteration":763,"passed_time":5.239175339,"remaining_time":1.618384005},
{"learn":[0.2028613059],"iteration":764,"passed_time":5.24598478,"remaining_time":1.611511664},
{"learn":[0.2027992698],"iteration":765,"passed_time":5.254294091,"remaining_time":1.605097673},
{"learn":[0.2027117837],"iteration":766,"passed_time":5.261245382,"remaining_time":1.598266198},
{"learn":[0.2026447186],"iteration":767,"passed_time":5.267911179,"remaining_time":1.591348169},
{"learn":[0.2026061132],"iteration":768,"passed_time":5.274881925,"remaining_time":1.584522399},
{"learn":[0.2025064015],"iteration":769,"passed_time":5.281965889,"remaining_time":1.577730071},
{"learn":[0.2023421668],"iteration":770,"passed_time":5.288785988,"remaining_time":1.570858614},
{"learn":[0.2023283433],"iteration":771,"passed_time":5.295531366,"remaining_time":1.563965222},
{"learn":[0.2021405746],"iteration":772,"passed_time":5.302158109,"remaining_time":1.557037375},
{"learn":[0.2020289028],"iteration":773,"passed_time":5.308597622,"remaining_time":1.550055636},
{"learn":[0.2017900921],"iteration":774,"passed_time":5.315391044,"remaining_time":1.543178045},
{"learn":[0.2015661902],"iteration":775,"passed_time":5.322615019,"remaining_time":1.536424954},
{"learn":[0.2013286948],"iteration":776,"passed_time":5.329633637,"remaining_time":1.529611713},
{"learn":[0.2011171176],"iteration":777,"passed_time":5.336136572,"remaining_time":1.522650796},
{"learn":[0.2010579709],"iteration":778,"passed_time":5.342720125,"remaining_time":1.515713925},
{"learn":[0.2010210024],"iteration":779,"passed_time":5.349590421,"remaining_time":1.508858837},
{"learn":[0.2008751582],"iteration":780,"passed_time":5.356594634,"remaining_time":1.502041261},
{"learn":[0.2007446266],"iteration":781,"passed_time":5.363476173,"remaining_time":1.49518901},
{"learn":[0.2006490822],"iteration":782,"passed_time":5.370430459,"remaining_time":1.488356845},
{"learn":[0.2005010152],"iteration":783,"passed_time":5.376971457,"remaining_time":1.481410503},
{"learn":[0.2004393775],"iteration":784,"passed_time":5.383788287,"remaining_time":1.474540741},
{"learn":[0.2003808495],"iteration":785,"passed_time":5.390800035,"remaining_time":1.467724183},
{"learn":[0.200316781],"iteration":786,"passed_time":5.397333058,"remaining_time":1.460777562},
{"learn":[0.2002471877],"iteration":787,"passed_time":5.404039271,"remaining_time":1.453878585},
{"learn":[0.2002142867],"iteration":788,"passed_time":5.41082892,"remaining_time":1.447002411},
{"learn":[0.2000764888],"iteration":789,"passed_time":5.417624076,"remaining_time":1.440127919},
{"learn":[0.1999331056],"iteration":790,"passed_time":5.424441901,"remaining_time":1.433259617},
{"learn":[0.1998704368],"iteration":791,"passed_time":5.431101543,"remaining_time":1.4263499},
{"learn":[0.1996850134],"iteration":792,"passed_time":5.437912296,"remaining_time":1.419480259},
{"learn":[0.1995719227],"iteration":793,"passed_time":5.444545792,"remaining_time":1.412564777},
{"learn":[0.1995293846],"iteration":794,"passed_time":5.451575604,"remaining_time":1.4057522},
{"learn":[0.1994978301],"iteration":795,"passed_time":5.45986453,"remaining_time":1.399261764},
{"learn":[0.1993357094],"iteration":796,"passed_time":5.466625795,"remaining_time":1.392377712},
{"learn":[0.1993240569],"iteration":797,"passed_time":5.473520796,"remaining_time":1.385527821},
{"learn":[0.1992911338],"iteration":798,"passed_time":5.48044498,"remaining_time":1.378685158},
{"learn":[0.1992479379],"iteration":799,"passed_time":5.487835942,"remaining_time":1.371958985},
{"learn":[0.1992260678],"iteration":800,"passed_time":5.494600678,"remaining_time":1.365075574},
{"learn":[0.1990573658],"iteration":801,"passed_time":5.501317829,"remaining_time":1.358180711},
{"learn":[0.1988839458],"iteration":802,"passed_time":5.508771407,"remaining_time":1.351466958},
{"learn":[0.1988685635],"iteration":803,"passed_time":5.515578183,"remaining_time":1.344593686},
{"learn":[0.1988369121],"iteration":804,"passed_time":5.52227652,"remaining_time":1.337694312},
{"learn":[0.1987730615],"iteration":805,"passed_time":5.529483686,"remaining_time":1.330917909},
{"learn":[0.1987258128],"iteration":806,"passed_time":5.537658257,"remaining_time":1.324371801},
{"learn":[0.1986061254],"iteration":807,"passed_time":5.544554804,"remaining_time":1.317517973},
{"learn":[0.1985132767],"iteration":808,"passed_time":5.551470819,"remaining_time":1.310668636},
{"learn":[0.198367628],"iteration":809,"passed_time":5.558158517,"remaining_time":1.303765578},
{"learn":[0.1982510341],"iteration":810,"passed_time":5.565299797,"remaining_time":1.296968757},
{"learn":[0.197913672],"iteration":811,"passed_time":5.57218733,"remaining_time":1.290112338},
{"learn":[0.1978635212],"iteration":812,"passed_time":5.579121963,"remaining_time":1.283266675},
{"learn":[0.197782171],"iteration":813,"passed_time":5.585833106,"remaining_time":1.276369727},
{"learn":[0.1977187674],"iteration":814,"passed_time":5.592693451,"remaining_time":1.269507102},
{"learn":[0.1976285547],"iteration":815,"passed_time":5.599401949,"remaining_time":1.262610243},
{"learn":[0.1975287973],"iteration":816,"passed_time":5.606378522,"remaining_time":1.255773892},
{"learn":[0.1975069788],"iteration":817,"passed_time":5.612831227,"remaining_time":1.24882064},
{"learn":[0.1974550882],"iteration":818,"passed_time":5.619434981,"remaining_time":1.241901992},
{"learn":[0.1972929686],"iteration":819,"passed_time":5.626191567,"remaining_time":1.235017661},
{"learn":[0.1971370884],"iteration":820,"passed_time":5.633249001,"remaining_time":1.228199234},
{"learn":[0.1969639624],"iteration":821,"passed_time":5.639904791,"remaining_time":1.221293251},
{"learn":[0.1969027874],"iteration":822,"passed_time":5.64636116,"remaining_time":1.214344988},
{"learn":[0.1968352545],"iteration":823,"passed_time":5.653075653,"remaining_time":1.207453052},
{"learn":[0.1968180224],"iteration":824,"passed_time":5.65997559,"remaining_time":1.200600883},
{"learn":[0.1965546247],"iteration":825,"passed_time":5.668327609,"remaining_time":1.194054484},
{"learn":[0.1964067075],"iteration":826,"passed_time":5.675244088,"remaining_time":1.187203419},
{"learn":[0.1962899284],"iteration":827,"passed_time":5.681940937,"remaining_time":1.180306571},
{"learn":[0.1961607479],"iteration":828,"passed_time":5.688674156,"remaining_time":1.173417709},
{"learn":[0.1960757702],"iteration":829,"passed_time":5.695501196,"remaining_time":1.166548438},
{"learn":[0.1959889838],"iteration":830,"passed_time":5.702283878,"remaining_time":1.159670247},
{"learn":[0.1959041373],"iteration":831,"passed_time":5.709157556,"remaining_time":1.15281066},
{"learn":[0.1958777912],"iteration":832,"passed_time":5.715758729,"remaining_time":1.145896408},
{"learn":[0.1957882067],"iteration":833,"passed_time":5.722327137,"remaining_time":1.138976385},
{"learn":[0.1956198002],"iteration":834,"passed_time":5.729372267,"remaining_time":1.132151406},
{"learn":[0.1955517111],"iteration":835,"passed_time":5.735976926,"remaining_time":1.125239493},
{"learn":[0.1955227515],"iteration":836,"passed_time":5.742684784,"remaining_time":1.118348411},
{"learn":[0.1953764886],"iteration":837,"passed_time":5.750912548,"remaining_time":1.11175159},
{"learn":[0.1953273247],"iteration":838,"passed_time":5.758579429,"remaining_time":1.105043252},
{"learn":[0.1953260926],"iteration":839,"passed_time":5.764251434,"remaining_time":1.097952654},
{"learn":[0.1952917251],"iteration":840,"passed_time":5.771523452,"remaining_time":1.09116793},
{"learn":[0.195269745],"iteration":841,"passed_time":5.779019303,"remaining_time":1.08442405},
{"learn":[0.1951901513],"iteration":842,"passed_time":5.785737675,"remaining_time":1.077533588},
{"learn":[0.1950072555],"iteration":843,"passed_time":5.792637869,"remaining_time":1.070677142},
{"learn":[0.1950039966],"iteration":844,"passed_time":5.799295387,"remaining_time":1.063776077},
{"learn":[0.1949213536],"iteration":845,"passed_time":5.805899551,"remaining_time":1.056865876},
{"learn":[0.1948185641],"iteration":846,"passed_time":5.812483389,"remaining_time":1.049952726},
{"learn":[0.1946801281],"iteration":847,"passed_time":5.819280098,"remaining_time":1.043078508},
{"learn":[0.1944868405],"iteration":848,"passed_time":5.826171873,"remaining_time":1.036221381},
{"learn":[0.1943094164],"iteration":849,"passed_time":5.833132607,"remaining_time":1.029376342},
{"learn":[0.1942546686],"iteration":850,"passed_time":5.839844964,"remaining_time":1.022487544},
{"learn":[0.1941848195],"iteration":851,"passed_time":5.846640317,"remaining_time":1.015613576},
{"learn":[0.1940675035],"iteration":852,"passed_time":5.853453204,"remaining_time":1.008742815},
{"learn":[0.1940285281],"iteration":853,"passed_time":5.860186352,"remaining_time":1.001858557},
{"learn":[0.1940269874],"iteration":854,"passed_time":5.864736596,"remaining_time":0.994604452},
{"learn":[0.194014849],"iteration":855,"passed_time":5.873302226,"remaining_time":0.9880321501},
{"learn":[0.1938433136],"iteration":856,"passed_time":5.879937433,"remaining_time":0.981133084},
{"learn":[0.1935122322],"iteration":857,"passed_time":5.886884032,"remaining_time":0.9742861685},
{"learn":[0.193482441],"iteration":858,"passed_time":5.893598751,"remaining_time":0.9674009592},
{"learn":[0.1934207194],"iteration":859,"passed_time":5.90108416,"remaining_time":0.9606416074},
{"learn":[0.1933565983],"iteration":860,"passed_time":5.908094238,"remaining_time":0.9538038316},
{"learn":[0.1932438309],"iteration":861,"passed_time":5.915361821,"remaining_time":0.9470068808},
{"learn":[0.1931577208],"iteration":862,"passed_time":5.923847394,"remaining_time":0.9404021934},
{"learn":[0.1930495157],"iteration":863,"passed_time":5.931762153,"remaining_time":0.9337033019},
{"learn":[0.1928632684],"iteration":864,"passed_time":5.940671214,"remaining_time":0.927156779},
{"learn":[0.1928280992],"iteration":865,"passed_time":5.94804241,"remaining_time":0.9203668394},
{"learn":[0.1927325772],"iteration":866,"passed_time":5.955055492,"remaining_time":0.9135206234},
{"learn":[0.1926077174],"iteration":867,"passed_time":5.962495961,"remaining_time":0.9067390171},
{"learn":[0.1924741797],"iteration":868,"passed_time":5.9690048,"remaining_time":0.8998154532},
{"learn":[0.192209136],"iteration":869,"passed_time":5.975397552,"remaining_time":0.8928754963},
{"learn":[0.1920325644],"iteration":870,"passed_time":5.981792846,"remaining_time":0.8859371724},
{"learn":[0.1919018418],"iteration":871,"passed_time":5.988429976,"remaining_time":0.8790355928},
{"learn":[0.191831863],"iteration":872,"passed_time":5.994683011,"remaining_time":0.8720787428},
{"learn":[0.1917252196],"iteration":873,"passed_time":6.001458342,"remaining_time":0.8651987998},
{"learn":[0.1917140816],"iteration":874,"passed_time":6.008009788,"remaining_time":0.8582871126},
{"learn":[0.1916494385],"iteration":875,"passed_time":6.01430406,"remaining_time":0.8513398442},
{"learn":[0.1916492887],"iteration":876,"passed_time":6.018975314,"remaining_time":0.8441664351},
{"learn":[0.1915841666],"iteration":877,"passed_time":6.025315436,"remaining_time":0.8372306187},
{"learn":[0.1915154872],"iteration":878,"passed_time":6.0319949,"remaining_time":0.8303428702},
{"learn":[0.1913918143],"iteration":879,"passed_time":6.038522471,"remaining_time":0.8234348825},
{"learn":[0.1912330538],"iteration":880,"passed_time":6.044925236,"remaining_time":0.8165109002},
{"learn":[0.1911538385],"iteration":881,"passed_time":6.05146114,"remaining_time":0.8096059122},
{"learn":[0.1909969984],"iteration":882,"passed_time":6.057944756,"remaining_time":0.8026948317},
{"learn":[0.1908684107],"iteration":883,"passed_time":6.064577067,"remaining_time":0.7958042305},
{"learn":[0.1906841409],"iteration":884,"passed_time":6.070960539,"remaining_time":0.7888818779},
{"learn":[0.1906701867],"iteration":885,"passed_time":6.079411515,"remaining_time":0.7822267638},
{"learn":[0.190617261],"iteration":886,"passed_time":6.086097057,"remaining_time":0.7753426916},
{"learn":[0.1905654007],"iteration":887,"passed_time":6.09256637,"remaining_time":0.7684317944},
{"learn":[0.1903809928],"iteration":888,"passed_time":6.099292432,"remaining_time":0.7615539482},
{"learn":[0.1902982925],"iteration":889,"passed_time":6.10564299,"remaining_time":0.7546300324},
{"learn":[0.1902461709],"iteration":890,"passed_time":6.112182019,"remaining_time":0.7477304603},
{"learn":[0.1902332695],"iteration":891,"passed_time":6.118716627,"remaining_time":0.7408311611},
{"learn":[0.19004084],"iteration":892,"passed_time":6.125313227,"remaining_time":0.7339401067},
{"learn":[0.1898952954],"iteration":893,"passed_time":6.131891417,"remaining_time":0.7270475282},
{"learn":[0.1897219617],"iteration":894,"passed_time":6.139217149,"remaining_time":0.7202433527},
{"learn":[0.1893918965],"iteration":895,"passed_time":6.146150933,"remaining_time":0.713392519},
{"learn":[0.1893047507],"iteration":896,"passed_time":6.152781081,"remaining_time":0.7065066348},
{"learn":[0.1892008905],"iteration":897,"passed_time":6.159223622,"remaining_time":0.6996000105},
{"learn":[0.1891435069],"iteration":898,"passed_time":6.165897332,"remaining_time":0.6927203899},
{"learn":[0.1889750524],"iteration":899,"passed_time":6.173529303,"remaining_time":0.6859477003},
{"learn":[0.1887272953],"iteration":900,"passed_time":6.180031758,"remaining_time":0.6790489945},
{"learn":[0.1885244835],"iteration":901,"passed_time":6.186574132,"remaining_time":0.6721555043},
{"learn":[0.1883776073],"iteration":902,"passed_time":6.193553128,"remaining_time":0.6653096937},
{"learn":[0.1881443461],"iteration":903,"passed_time":6.200372563,"remaining_time":0.6584466438},
{"learn":[0.1879836712],"iteration":904,"passed_time":6.2069928,"remaining_time":0.6515627801},
{"learn":[0.1878588766],"iteration":905,"passed_time":6.213608945,"remaining_time":0.6446790737},
{"learn":[0.1877309962],"iteration":906,"passed_time":6.220267285,"remaining_time":0.6378002839},
{"learn":[0.1876986265],"iteration":907,"passed_time":6.226815044,"remaining_time":0.6309107754},
{"learn":[0.1876391536],"iteration":908,"passed_time":6.233030281,"remaining_time":0.62398873},
{"learn":[0.1874965184],"iteration":909,"passed_time":6.23930283,"remaining_time":0.6170739062},
{"learn":[0.1873459627],"iteration":910,"passed_time":6.245975276,"remaining_time":0.6101995604},
{"learn":[0.1872764509],"iteration":911,"passed_time":6.252625092,"remaining_time":0.6033234738},
{"learn":[0.1871984333],"iteration":912,"passed_time":6.259340101,"remaining_time":0.5964540951},
{"learn":[0.1869882324],"iteration":913,"passed_time":6.265850768,"remaining_time":0.5895658272},
{"learn":[0.1867126697],"iteration":914,"passed_time":6.273302983,"remaining_time":0.5827658509},
{"learn":[0.1866968267],"iteration":915,"passed_time":6.281006858,"remaining_time":0.5759875284},
{"learn":[0.1866425676],"iteration":916,"passed_time":6.2873288,"remaining_time":0.5690821051},
{"learn":[0.1865868333],"iteration":917,"passed_time":6.293842366,"remaining_time":0.5621950698},
{"learn":[0.1864993881],"iteration":918,"passed_time":6.3006607,"remaining_time":0.5553357091},
{"learn":[0.1864839133],"iteration":919,"passed_time":6.307458823,"remaining_time":0.5484746803},
{"learn":[0.1864427416],"iteration":920,"passed_time":6.31391936,"remaining_time":0.5415848311},
{"learn":[0.1863364822],"iteration":921,"passed_time":6.320650156,"remaining_time":0.5347187768},
{"learn":[0.1863038189],"iteration":922,"passed_time":6.327214488,"remaining_time":0.5278391284},
{"learn":[0.1862847728],"iteration":923,"passed_time":6.333957705,"remaining_time":0.5209748761},
{"learn":[0.1862459416],"iteration":924,"passed_time":6.340567347,"remaining_time":0.5141000552},
{"learn":[0.1861609072],"iteration":925,"passed_time":6.347187435,"remaining_time":0.5072266416},
{"learn":[0.1861318303],"iteration":926,"passed_time":6.353718226,"remaining_time":0.5003467427},
{"learn":[0.1860261952],"iteration":927,"passed_time":6.36046458,"remaining_time":0.4934843208},
{"learn":[0.1858462369],"iteration":928,"passed_time":6.367411683,"remaining_time":0.4866374914},
{"learn":[0.1858447479],"iteration":929,"passed_time":6.37402733,"remaining_time":0.479765498},
{"learn":[0.1858049479],"iteration":930,"passed_time":6.381535456,"remaining_time":0.4729602003},
{"learn":[0.1857834507],"iteration":931,"passed_time":6.388756817,"remaining_time":0.4661324716},
{"learn":[0.1856824285],"iteration":932,"passed_time":6.395618595,"remaining_time":0.459278077},
{"learn":[0.1856242779],"iteration":933,"passed_time":6.402403655,"remaining_time":0.4524182454},
{"learn":[0.1855834889],"iteration":934,"passed_time":6.409781393,"remaining_time":0.445599776},
{"learn":[0.1855137714],"iteration":935,"passed_time":6.416816082,"remaining_time":0.4387566552},
{"learn":[0.1853210176],"iteration":936,"passed_time":6.423746201,"remaining_time":0.4319060946},
{"learn":[0.1852703979],"iteration":937,"passed_time":6.430621312,"remaining_time":0.4250517285},
{"learn":[0.1852212476],"iteration":938,"passed_time":6.438184172,"remaining_time":0.4182419962},
{"learn":[0.1851382575],"iteration":939,"passed_time":6.444969063,"remaining_time":0.411381004},
{"learn":[0.185033943],"iteration":940,"passed_time":6.45193212,"remaining_time":0.4045313444},
{"learn":[0.1849797276],"iteration":941,"passed_time":6.458580261,"remaining_time":0.3976620543},
{"learn":[0.1848109357],"iteration":942,"passed_time":6.465473369,"remaining_time":0.3908080403},
{"learn":[0.1846891287],"iteration":943,"passed_time":6.474285166,"remaining_time":0.3840677641},
{"learn":[0.1845650488],"iteration":944,"passed_time":6.481322813,"remaining_time":0.3772198463},
{"learn":[0.1845143504],"iteration":945,"passed_time":6.488843373,"remaining_time":0.3703990932},
{"learn":[0.1844653669],"iteration":946,"passed_time":6.495787896,"remaining_time":0.3635446236},
{"learn":[0.1842699171],"iteration":947,"passed_time":6.503136198,"remaining_time":0.3567121121},
{"learn":[0.1842337478],"iteration":948,"passed_time":6.50981039,"remaining_time":0.3498422865},
{"learn":[0.1841933418],"iteration":949,"passed_time":6.51696028,"remaining_time":0.3429979095},
{"learn":[0.1841676528],"iteration":950,"passed_time":6.523818482,"remaining_time":0.3361378608},
{"learn":[0.1841115434],"iteration":951,"passed_time":6.530673925,"remaining_time":0.3292776769},
{"learn":[0.184000106],"iteration":952,"passed_time":6.53713133,"remaining_time":0.3223978725},
{"learn":[0.1839614289],"iteration":953,"passed_time":6.543594387,"remaining_time":0.3155192262},
{"learn":[0.1838999301],"iteration":954,"passed_time":6.550260097,"remaining_time":0.3086509993},
{"learn":[0.1838608937],"iteration":955,"passed_time":6.556983276,"remaining_time":0.3017858411},
{"learn":[0.1837687596],"iteration":956,"passed_time":6.563908596,"remaining_time":0.2949300623},
{"learn":[0.1835819505],"iteration":957,"passed_time":6.570889193,"remaining_time":0.2880765617},
{"learn":[0.1835412107],"iteration":958,"passed_time":6.578018177,"remaining_time":0.28122914},
{"learn":[0.1834671761],"iteration":959,"passed_time":6.584918757,"remaining_time":0.2743716149},
{"learn":[0.1833959638],"iteration":960,"passed_time":6.591861846,"remaining_time":0.2675157253},
{"learn":[0.1833569399],"iteration":961,"passed_time":6.598651734,"remaining_time":0.2606536028},
{"learn":[0.1833033989],"iteration":962,"passed_time":6.60534778,"remaining_time":0.2537880248},
{"learn":[0.1832261259],"iteration":963,"passed_time":6.6120797,"remaining_time":0.2469241382},
{"learn":[0.1831350494],"iteration":964,"passed_time":6.618835722,"remaining_time":0.2400613993},
{"learn":[0.1830274624],"iteration":965,"passed_time":6.625741045,"remaining_time":0.2332041362},
{"learn":[0.1829093249],"iteration":966,"passed_time":6.63280711,"remaining_time":0.2263522592},
{"learn":[0.1828113405],"iteration":967,"passed_time":6.639764756,"remaining_time":0.2194963556},
{"learn":[0.1826717702],"iteration":968,"passed_time":6.646438192,"remaining_time":0.2126311496},
{"learn":[0.1824855686],"iteration":969,"passed_time":6.653337877,"remaining_time":0.2057733364},
{"learn":[0.1824289128],"iteration":970,"passed_time":6.660430169,"remaining_time":0.1989211894},
{"learn":[0.1824166318],"iteration":971,"passed_time":6.667518022,"remaining_time":0.1920684204},
{"learn":[0.1823351961],"iteration":972,"passed_time":6.67609987,"remaining_time":0.1852566254},
{"learn":[0.1822726477],"iteration":973,"passed_time":6.683029023,"remaining_time":0.1783970786},
{"learn":[0.1821771922],"iteration":974,"passed_time":6.689586558,"remaining_time":0.1715278605},
{"learn":[0.1821766133],"iteration":975,"passed_time":6.695163942,"remaining_time":0.1646351789},
{"learn":[0.1820969203],"iteration":976,"passed_time":6.702318222,"remaining_time":0.1577823123},
{"learn":[0.1820154014],"iteration":977,"passed_time":6.709239272,"remaining_time":0.1509235828},
{"learn":[0.1819344244],"iteration":978,"passed_time":6.716585226,"remaining_time":0.1440738404},
{"learn":[0.1817969239],"iteration":979,"passed_time":6.723864237,"remaining_time":0.1372217191},
{"learn":[0.1817110468],"iteration":980,"passed_time":6.730890449,"remaining_time":0.1303638313},
{"learn":[0.1816944382],"iteration":981,"passed_time":6.737562958,"remaining_time":0.1234991173},
{"learn":[0.1816925344],"iteration":982,"passed_time":6.744604084,"remaining_time":0.1166411693},
{"learn":[0.1815019361],"iteration":983,"passed_time":6.750998044,"remaining_time":0.1097723259},
{"learn":[0.1813899707],"iteration":984,"passed_time":6.757543833,"remaining_time":0.1029067589},
{"learn":[0.1812954482],"iteration":985,"passed_time":6.764122965,"remaining_time":0.0960423139},
{"learn":[0.1812791039],"iteration":986,"passed_time":6.770714296,"remaining_time":0.08917860774},
{"learn":[0.1812289151],"iteration":987,"passed_time":6.777413558,"remaining_time":0.08231676387},
{"learn":[0.1811536127],"iteration":988,"passed_time":6.784554269,"remaining_time":0.0754601587},
{"learn":[0.181030824],"iteration":989,"passed_time":6.791988601,"remaining_time":0.06860594546},
{"learn":[0.1809881296],"iteration":990,"passed_time":6.798911639,"remaining_time":0.06174591801},
{"learn":[0.180985043],"iteration":991,"passed_time":6.805678108,"remaining_time":0.05488450087},
{"learn":[0.1807417313],"iteration":992,"passed_time":6.812586892,"remaining_time":0.04802427819},
{"learn":[0.1805967517],"iteration":993,"passed_time":6.819247462,"remaining_time":0.04116245953},
{"learn":[0.1805396358],"iteration":994,"passed_time":6.825940792,"remaining_time":0.03430121001},
{"learn":[0.1805136255],"iteration":995,"passed_time":6.832709225,"remaining_time":0.0274405993},
{"learn":[0.180427314],"iteration":996,"passed_time":6.839557639,"remaining_time":0.02058041416},
{"learn":[0.1802233467],"iteration":997,"passed_time":6.84643621,"remaining_time":0.01372031305},
{"learn":[0.1801593597],"iteration":998,"passed_time":6.853086478,"remaining_time":0.006859946424},
{"learn":[0.1800580774],"iteration":999,"passed_time":6.859911511,"remaining_time":0}
]}